Workbook

Sheet input
A1: FINANCIAL FLOOR DECISION LAB — INPUT
A2: Blue cells = inputs you edit. Do not edit formulas in other sheets.
A4: PROFILE
A5: current_age | B5: 38
A6: monthly_income | B6: 4800
A7: monthly_expense | B7: 3000
A8: cash | B8: 19124
A9: brokerage | B9: 76009
A10: retirement_accounts | B10: 71943
A11: monthly_401k | B11: 1958
A13: RETIREMENT
A14: expected_return | B14: 0.07
A15: withdrawal_rate | B15: 0.04
A16: target_monthly_spend | B16: 8333
A17: social_security_monthly | B17: 0
A18: retirement_invest_mo | B18: 800
A20: GOALS
A21: goal_name | B21: target_amount | C21: monthly_alloc
A22: Trading Seed | B22: 250000 | C22: 200
A23: Grad School Fund | B23: 40000 | C23: 300
A24: House Down Payment | B24: 80000 | C24: 500
A26: SCENARIOS
A27: scenario_name | B27: scenario_type | C27: active_flag | D27: pause_401k | E27: start_offset_yr | F27: duration_mo | G27: income_change_pct | H27: one_time_cost | I27: expense_delta_mo | J27: contrib_delta_mo | K27: recovery_income_pct
A28: Baseline | B28: baseline | C28: =TRUE() -> TRUE | D28: =FALSE() -> FALSE | E28: 0 | F28: 0 | G28: 0 | H28: 0 | I28: 0 | J28: 0 | K28: 1
A29: Career Break 1yr | B29: flow_shock | C29: =TRUE() -> TRUE | D29: =TRUE() -> TRUE | E29: 1 | F29: 12 | G29: -1 | H29: 0 | I29: 0 | J29: -800 | K29: 1
A30: Grad School 2yr | B30: hybrid | C30: =TRUE() -> TRUE | D30: =TRUE() -> TRUE | E30: 2 | F30: 24 | G30: -0.5 | H30: 40000 | I30: 300 | J30: -800 | K30: 1
A31: Family Planning | B31: flow_shock | C31: =TRUE() -> TRUE | D31: =FALSE() -> FALSE | E31: 1 | F31: 12 | G31: 0 | H31: 0 | I31: 500 | J31: 0 | K31: 1

Sheet calc_is
A1: INCOME STATEMENT (IS) — Flow Constraints
A2: INCOME STATEMENT
A3: monthly_income | B3: =input!B6 -> 4800
A4: monthly_expense | B4: =input!B7 -> 3000
A5: surplus | B5: =B3-B4 -> 1800
A7: monthly_401k | B7: =input!B11 -> 1958
A8: annual_401k | B8: =B7*12 -> 23496
A10: cash | B10: =input!B8 -> 19124
A11: brokerage | B11: =input!B9 -> 76009
A12: retirement_accounts | B12: =input!B10 -> 71943
A13: starting_invested_assets | B13: =B11+B12 -> 147952
A14: total_assets | B14: =B10+B11+B12 -> 167076
A16: survival_months | B16: =IFERROR(B10/B4,0) -> 6.3746667
A17: current_age | B17: =input!B5 -> 38

Sheet calc_cf
A1: CASH FLOW (CF) — Allocation Waterfall
A2: ALLOCATION WATERFALL
A3: surplus | B3: =calc_is!B5 -> 1800
A4: mandatory_401k_monthly | B4: =calc_is!B7 -> 1958
A6: retirement_invest_monthly | B6: =input!B18 -> 800
A7: retirement_invest_monthly_cap | B7: =MAX(0,MIN(B6,calc_is!B5)) -> 800
A9: goal_alloc_total_monthly | B9: =SUM(B12:B14) -> 1000
A10: surplus_after_retire | B10: =MAX(0,B3-B7) -> 1000
A11: GOAL ALLOCATION (Surplus-Capped)
A12: =input!C22 -> 200 | B12: =MIN(input!C22, MAX(0, B10)) -> 200 | C12: =IFERROR(input!B22, 0) -> 250000 | D12: =IFERROR((input!B22)/MAX(1,B12)*12, 0) -> 15000
A13: =input!C23 -> 300 | B13: =MIN(input!C23, MAX(0, B10-B12)) -> 300 | C13: =IFERROR(input!B23, 0) -> 40000 | D13: =IFERROR((input!B23)/MAX(1,B13)*12, 0) -> 1600
A14: =input!C24 -> 500 | B14: =MIN(input!C24, MAX(0, B10-B12-B13)) -> 500 | C14: =IFERROR(input!B24, 0) -> 80000 | D14: =IFERROR((input!B24)/MAX(1,B14)*12, 0) -> 1920
A16: GOAL ACHIEVE AGE
A17: goal_name | B17: achieve_age | C17: months_remaining
A18: =input!C22 -> 200 | B18: =IFERROR(input!B5+B12/12, 999) -> 54.666667 | C18: =B12 -> 200
A19: =input!C23 -> 300 | B19: =IFERROR(input!B5+B13/12, 999) -> 63 | C19: =B13 -> 300
A20: =input!C24 -> 500 | B20: =IFERROR(input!B5+B14/12, 999) -> 79.666667 | C20: =B14 -> 500
A22: RESIDUAL CASH
A23: cash_residual_monthly | B23: =MAX(0,B3-B7-B9) -> 0
A24: total_allocated_monthly | B24: =B7+B9 -> 1800

Sheet calc_bs
A1: BALANCE SHEET (BS) — Stock State
A2: CURRENT BALANCE SHEET
A3: cash | B3: =calc_is!B10 -> 19124
A4: brokerage | B4: =calc_is!B11 -> 76009
A5: retirement_accounts | B5: =calc_is!B12 -> 71943
A6: starting_invested_assets | B6: =calc_is!B13 -> 147952
A7: total_assets | B7: =calc_is!B14 -> 167076
A9: safe_layer_target | B9: =calc_metrics!B4 -> 2499900
A10: safe_layer_progress | B10: =IFERROR(B6/B9,0) -> 0.059183167
A11: surplus_allocated_check | B11: =calc_cf!B24 -> 1800

Sheet calc_metrics
A1: METRICS — Primary KPIs
A2: CORE METRICS
A3: target_floor_annual_spend | B3: =input!B16*12 -> 99996
A4: safe_layer_target | B4: =IFERROR((B3-input!B17*12)/input!B15,0) -> 2499900
A5: liquid_invested_assets | B5: =calc_is!B13 -> 147952
A6: safe_layer_progress | B6: =IFERROR(B5/B4,0) -> 0.059183167
A7: survival_months | B7: =calc_is!B16 -> 6.3746667
A9: floor_age | B9: =B16 -> 61
A10: years_to_stability | B10: =IFERROR(B9-input!B5,0) -> 23
A11: investment_rate | B11: =IFERROR((calc_cf!B7+calc_is!B7)*12/(input!B6*12),0) -> 0.57458333
A12: total_monthly_invest | B12: =IFERROR(calc_cf!B7+calc_is!B7,0) -> 2758
A14: SCENARIO SUMMARY
A15: scenario_name | B15: floor_age | C15: delta_vs_baseline
A16: SCN000 | B16: 61 | C16: 0
A17: SCN001 | B17: 61 | C17: 0
A18: SCN002 | B18: 62 | C18: 1
A19: SCN003 | B19: 61 | C19: 0

Sheet projection
A1: scenario_id | B1: scenario_name | C1: projection_year_index | D1: age | E1: age_in_year | F1: income_annual | G1: expense_annual | H1: surplus_annual | I1: contrib_annual | J1: assets_start | K1: assets_end | L1: cash_balance | M1: safe_layer_target | N1: floor_reached_flag | O1: safe_layer_progress | P1: feasible_flag | Q1: survival_months | R1: scenario_type
A2: SCN000 | B2: Baseline | C2: 0 | D2: 0 | E2: =input!B5+0 -> 38 | F2: =input!B6*12 -> 57600 | G2: =input!B7*12 -> 36000 | H2: =F2-G2 -> 21600 | I2: =input!B11*12+MAX(0, MIN(input!B18, H2/12)) * 12 -> 33096 | J2: =calc_is!B13 -> 147952 | K2: =J2*(1+input!B14)+I2*((1+input!B14)-1)/input!B14 -> 191404.64 | L2: =input!B8 -> 19124 | M2: =calc_metrics!B4 -> 2499900 | N2: =IF(K2>=M2,"TRUE","FALSE") -> FALSE | O2: =IFERROR(K2/M2,0) -> 0.076564919 | P2: =IF(AND(L2>=0,Q2>=6,K2>=M2*0.25),"TRUE","FALSE") -> FALSE | Q2: =IFERROR(L2/(input!B7),0) -> 6.3746667 | R2: baseline
A3: SCN000 | B3: Baseline | C3: 1 | D3: 1 | E3: =input!B5+1 -> 39 | F3: =input!B6*12 -> 57600 | G3: =input!B7*12 -> 36000 | H3: =F3-G3 -> 21600 | I3: =input!B11*12+MAX(0, MIN(input!B18, H3/12)) * 12 -> 33096 | J3: =K2 -> 191404.64 | K3: =J3*(1+input!B14)+I3*((1+input!B14)-1)/input!B14 -> 237898.96 | L3: =L2+MAX(0,H3/12) -> 20924 | M3: =calc_metrics!B4 -> 2499900 | N3: =IF(K3>=M3,"TRUE","FALSE") -> FALSE | O3: =IFERROR(K3/M3,0) -> 0.095163392 | P3: =IF(AND(L3>=0,Q3>=6,K3>=M3*0.25),"TRUE","FALSE") -> FALSE | Q3: =IFERROR(L3/(input!B7),0) -> 6.9746667 | R3: baseline
A4: SCN000 | B4: Baseline | C4: 2 | D4: 2 | E4: =input!B5+2 -> 40 | F4: =input!B6*12 -> 57600 | G4: =input!B7*12 -> 36000 | H4: =F4-G4 -> 21600 | I4: =input!B11*12+MAX(0, MIN(input!B18, H4/12)) * 12 -> 33096 | J4: =K3 -> 237898.96 | K4: =J4*(1+input!B14)+I4*((1+input!B14)-1)/input!B14 -> 287647.89 | L4: =L3+MAX(0,H4/12) -> 22724 | M4: =calc_metrics!B4 -> 2499900 | N4: =IF(K4>=M4,"TRUE","FALSE") -> FALSE | O4: =IFERROR(K4/M4,0) -> 0.11506376 | P4: =IF(AND(L4>=0,Q4>=6,K4>=M4*0.25),"TRUE","FALSE") -> FALSE | Q4: =IFERROR(L4/(input!B7),0) -> 7.5746667 | R4: baseline
A5: SCN000 | B5: Baseline | C5: 3 | D5: 3 | E5: =input!B5+3 -> 41 | F5: =input!B6*12 -> 57600 | G5: =input!B7*12 -> 36000 | H5: =F5-G5 -> 21600 | I5: =input!B11*12+MAX(0, MIN(input!B18, H5/12)) * 12 -> 33096 | J5: =K4 -> 287647.89 | K5: =J5*(1+input!B14)+I5*((1+input!B14)-1)/input!B14 -> 340879.24 | L5: =L4+MAX(0,H5/12) -> 24524 | M5: =calc_metrics!B4 -> 2499900 | N5: =IF(K5>=M5,"TRUE","FALSE") -> FALSE | O5: =IFERROR(K5/M5,0) -> 0.13635715 | P5: =IF(AND(L5>=0,Q5>=6,K5>=M5*0.25),"TRUE","FALSE") -> FALSE | Q5: =IFERROR(L5/(input!B7),0) -> 8.1746667 | R5: baseline
A6: SCN000 | B6: Baseline | C6: 4 | D6: 4 | E6: =input!B5+4 -> 42 | F6: =input!B6*12 -> 57600 | G6: =input!B7*12 -> 36000 | H6: =F6-G6 -> 21600 | I6: =input!B11*12+MAX(0, MIN(input!B18, H6/12)) * 12 -> 33096 | J6: =K5 -> 340879.24 | K6: =J6*(1+input!B14)+I6*((1+input!B14)-1)/input!B14 -> 397836.79 | L6: =L5+MAX(0,H6/12) -> 26324 | M6: =calc_metrics!B4 -> 2499900 | N6: =IF(K6>=M6,"TRUE","FALSE") -> FALSE | O6: =IFERROR(K6/M6,0) -> 0.15914108 | P6: =IF(AND(L6>=0,Q6>=6,K6>=M6*0.25),"TRUE","FALSE") -> FALSE | Q6: =IFERROR(L6/(input!B7),0) -> 8.7746667 | R6: baseline
A7: SCN000 | B7: Baseline | C7: 5 | D7: 5 | E7: =input!B5+5 -> 43 | F7: =input!B6*12 -> 57600 | G7: =input!B7*12 -> 36000 | H7: =F7-G7 -> 21600 | I7: =input!B11*12+MAX(0, MIN(input!B18, H7/12)) * 12 -> 33096 | J7: =K6 -> 397836.79 | K7: =J7*(1+input!B14)+I7*((1+input!B14)-1)/input!B14 -> 458781.37 | L7: =L6+MAX(0,H7/12) -> 28124 | M7: =calc_metrics!B4 -> 2499900 | N7: =IF(K7>=M7,"TRUE","FALSE") -> FALSE | O7: =IFERROR(K7/M7,0) -> 0.18351989 | P7: =IF(AND(L7>=0,Q7>=6,K7>=M7*0.25),"TRUE","FALSE") -> FALSE | Q7: =IFERROR(L7/(input!B7),0) -> 9.3746667 | R7: baseline
A8: SCN000 | B8: Baseline | C8: 6 | D8: 6 | E8: =input!B5+6 -> 44 | F8: =input!B6*12 -> 57600 | G8: =input!B7*12 -> 36000 | H8: =F8-G8 -> 21600 | I8: =input!B11*12+MAX(0, MIN(input!B18, H8/12)) * 12 -> 33096 | J8: =K7 -> 458781.37 | K8: =J8*(1+input!B14)+I8*((1+input!B14)-1)/input!B14 -> 523992.06 | L8: =L7+MAX(0,H8/12) -> 29924 | M8: =calc_metrics!B4 -> 2499900 | N8: =IF(K8>=M8,"TRUE","FALSE") -> FALSE | O8: =IFERROR(K8/M8,0) -> 0.20960521 | P8: =IF(AND(L8>=0,Q8>=6,K8>=M8*0.25),"TRUE","FALSE") -> FALSE | Q8: =IFERROR(L8/(input!B7),0) -> 9.9746667 | R8: baseline
A9: SCN000 | B9: Baseline | C9: 7 | D9: 7 | E9: =input!B5+7 -> 45 | F9: =input!B6*12 -> 57600 | G9: =input!B7*12 -> 36000 | H9: =F9-G9 -> 21600 | I9: =input!B11*12+MAX(0, MIN(input!B18, H9/12)) * 12 -> 33096 | J9: =K8 -> 523992.06 | K9: =J9*(1+input!B14)+I9*((1+input!B14)-1)/input!B14 -> 593767.51 | L9: =L8+MAX(0,H9/12) -> 31724 | M9: =calc_metrics!B4 -> 2499900 | N9: =IF(K9>=M9,"TRUE","FALSE") -> FALSE | O9: =IFERROR(K9/M9,0) -> 0.2375165 | P9: =IF(AND(L9>=0,Q9>=6,K9>=M9*0.25),"TRUE","FALSE") -> FALSE | Q9: =IFERROR(L9/(input!B7),0) -> 10.574667 | R9: baseline
A10: SCN000 | B10: Baseline | C10: 8 | D10: 8 | E10: =input!B5+8 -> 46 | F10: =input!B6*12 -> 57600 | G10: =input!B7*12 -> 36000 | H10: =F10-G10 -> 21600 | I10: =input!B11*12+MAX(0, MIN(input!B18, H10/12)) * 12 -> 33096 | J10: =K9 -> 593767.51 | K10: =J10*(1+input!B14)+I10*((1+input!B14)-1)/input!B14 -> 668427.23 | L10: =L9+MAX(0,H10/12) -> 33524 | M10: =calc_metrics!B4 -> 2499900 | N10: =IF(K10>=M10,"TRUE","FALSE") -> FALSE | O10: =IFERROR(K10/M10,0) -> 0.26738159 | P10: =IF(AND(L10>=0,Q10>=6,K10>=M10*0.25),"TRUE","FALSE") -> TRUE | Q10: =IFERROR(L10/(input!B7),0) -> 11.174667 | R10: baseline
A11: SCN000 | B11: Baseline | C11: 9 | D11: 9 | E11: =input!B5+9 -> 47 | F11: =input!B6*12 -> 57600 | G11: =input!B7*12 -> 36000 | H11: =F11-G11 -> 21600 | I11: =input!B11*12+MAX(0, MIN(input!B18, H11/12)) * 12 -> 33096 | J11: =K10 -> 668427.23 | K11: =J11*(1+input!B14)+I11*((1+input!B14)-1)/input!B14 -> 748313.14 | L11: =L10+MAX(0,H11/12) -> 35324 | M11: =calc_metrics!B4 -> 2499900 | N11: =IF(K11>=M11,"TRUE","FALSE") -> FALSE | O11: =IFERROR(K11/M11,0) -> 0.29933723 | P11: =IF(AND(L11>=0,Q11>=6,K11>=M11*0.25),"TRUE","FALSE") -> TRUE | Q11: =IFERROR(L11/(input!B7),0) -> 11.774667 | R11: baseline
A12: SCN000 | B12: Baseline | C12: 10 | D12: 10 | E12: =input!B5+10 -> 48 | F12: =input!B6*12 -> 57600 | G12: =input!B7*12 -> 36000 | H12: =F12-G12 -> 21600 | I12: =input!B11*12+MAX(0, MIN(input!B18, H12/12)) * 12 -> 33096 | J12: =K11 -> 748313.14 | K12: =J12*(1+input!B14)+I12*((1+input!B14)-1)/input!B14 -> 833791.06 | L12: =L11+MAX(0,H12/12) -> 37124 | M12: =calc_metrics!B4 -> 2499900 | N12: =IF(K12>=M12,"TRUE","FALSE") -> FALSE | O12: =IFERROR(K12/M12,0) -> 0.33352976 | P12: =IF(AND(L12>=0,Q12>=6,K12>=M12*0.25),"TRUE","FALSE") -> TRUE | Q12: =IFERROR(L12/(input!B7),0) -> 12.374667 | R12: baseline
A13: SCN000 | B13: Baseline | C13: 11 | D13: 11 | E13: =input!B5+11 -> 49 | F13: =input!B6*12 -> 57600 | G13: =input!B7*12 -> 36000 | H13: =F13-G13 -> 21600 | I13: =input!B11*12+MAX(0, MIN(input!B18, H13/12)) * 12 -> 33096 | J13: =K12 -> 833791.06 | K13: =J13*(1+input!B14)+I13*((1+input!B14)-1)/input!B14 -> 925252.43 | L13: =L12+MAX(0,H13/12) -> 38924 | M13: =calc_metrics!B4 -> 2499900 | N13: =IF(K13>=M13,"TRUE","FALSE") -> FALSE | O13: =IFERROR(K13/M13,0) -> 0.37011578 | P13: =IF(AND(L13>=0,Q13>=6,K13>=M13*0.25),"TRUE","FALSE") -> TRUE | Q13: =IFERROR(L13/(input!B7),0) -> 12.974667 | R13: baseline
A14: SCN000 | B14: Baseline | C14: 12 | D14: 12 | E14: =input!B5+12 -> 50 | F14: =input!B6*12 -> 57600 | G14: =input!B7*12 -> 36000 | H14: =F14-G14 -> 21600 | I14: =input!B11*12+MAX(0, MIN(input!B18, H14/12)) * 12 -> 33096 | J14: =K13 -> 925252.43 | K14: =J14*(1+input!B14)+I14*((1+input!B14)-1)/input!B14 -> 1023116.1 | L14: =L13+MAX(0,H14/12) -> 40724 | M14: =calc_metrics!B4 -> 2499900 | N14: =IF(K14>=M14,"TRUE","FALSE") -> FALSE | O14: =IFERROR(K14/M14,0) -> 0.40926281 | P14: =IF(AND(L14>=0,Q14>=6,K14>=M14*0.25),"TRUE","FALSE") -> TRUE | Q14: =IFERROR(L14/(input!B7),0) -> 13.574667 | R14: baseline
A15: SCN000 | B15: Baseline | C15: 13 | D15: 13 | E15: =input!B5+13 -> 51 | F15: =input!B6*12 -> 57600 | G15: =input!B7*12 -> 36000 | H15: =F15-G15 -> 21600 | I15: =input!B11*12+MAX(0, MIN(input!B18, H15/12)) * 12 -> 33096 | J15: =K14 -> 1023116.1 | K15: =J15*(1+input!B14)+I15*((1+input!B14)-1)/input!B14 -> 1127830.2 | L15: =L14+MAX(0,H15/12) -> 42524 | M15: =calc_metrics!B4 -> 2499900 | N15: =IF(K15>=M15,"TRUE","FALSE") -> FALSE | O15: =IFERROR(K15/M15,0) -> 0.45115014 | P15: =IF(AND(L15>=0,Q15>=6,K15>=M15*0.25),"TRUE","FALSE") -> TRUE | Q15: =IFERROR(L15/(input!B7),0) -> 14.174667 | R15: baseline
A16: SCN000 | B16: Baseline | C16: 14 | D16: 14 | E16: =input!B5+14 -> 52 | F16: =input!B6*12 -> 57600 | G16: =input!B7*12 -> 36000 | H16: =F16-G16 -> 21600 | I16: =input!B11*12+MAX(0, MIN(input!B18, H16/12)) * 12 -> 33096 | J16: =K15 -> 1127830.2 | K16: =J16*(1+input!B14)+I16*((1+input!B14)-1)/input!B14 -> 1239874.3 | L16: =L15+MAX(0,H16/12) -> 44324 | M16: =calc_metrics!B4 -> 2499900 | N16: =IF(K16>=M16,"TRUE","FALSE") -> FALSE | O16: =IFERROR(K16/M16,0) -> 0.49596958 | P16: =IF(AND(L16>=0,Q16>=6,K16>=M16*0.25),"TRUE","FALSE") -> TRUE | Q16: =IFERROR(L16/(input!B7),0) -> 14.774667 | R16: baseline
A17: SCN000 | B17: Baseline | C17: 15 | D17: 15 | E17: =input!B5+15 -> 53 | F17: =input!B6*12 -> 57600 | G17: =input!B7*12 -> 36000 | H17: =F17-G17 -> 21600 | I17: =input!B11*12+MAX(0, MIN(input!B18, H17/12)) * 12 -> 33096 | J17: =K16 -> 1239874.3 | K17: =J17*(1+input!B14)+I17*((1+input!B14)-1)/input!B14 -> 1359761.6 | L17: =L16+MAX(0,H17/12) -> 46124 | M17: =calc_metrics!B4 -> 2499900 | N17: =IF(K17>=M17,"TRUE","FALSE") -> FALSE | O17: =IFERROR(K17/M17,0) -> 0.54392638 | P17: =IF(AND(L17>=0,Q17>=6,K17>=M17*0.25),"TRUE","FALSE") -> TRUE | Q17: =IFERROR(L17/(input!B7),0) -> 15.374667 | R17: baseline
A18: SCN000 | B18: Baseline | C18: 16 | D18: 16 | E18: =input!B5+16 -> 54 | F18: =input!B6*12 -> 57600 | G18: =input!B7*12 -> 36000 | H18: =F18-G18 -> 21600 | I18: =input!B11*12+MAX(0, MIN(input!B18, H18/12)) * 12 -> 33096 | J18: =K17 -> 1359761.6 | K18: =J18*(1+input!B14)+I18*((1+input!B14)-1)/input!B14 -> 1488040.9 | L18: =L17+MAX(0,H18/12) -> 47924 | M18: =calc_metrics!B4 -> 2499900 | N18: =IF(K18>=M18,"TRUE","FALSE") -> FALSE | O18: =IFERROR(K18/M18,0) -> 0.59524015 | P18: =IF(AND(L18>=0,Q18>=6,K18>=M18*0.25),"TRUE","FALSE") -> TRUE | Q18: =IFERROR(L18/(input!B7),0) -> 15.974667 | R18: baseline
A19: SCN000 | B19: Baseline | C19: 17 | D19: 17 | E19: =input!B5+17 -> 55 | F19: =input!B6*12 -> 57600 | G19: =input!B7*12 -> 36000 | H19: =F19-G19 -> 21600 | I19: =input!B11*12+MAX(0, MIN(input!B18, H19/12)) * 12 -> 33096 | J19: =K18 -> 1488040.9 | K19: =J19*(1+input!B14)+I19*((1+input!B14)-1)/input!B14 -> 1625299.7 | L19: =L18+MAX(0,H19/12) -> 49724 | M19: =calc_metrics!B4 -> 2499900 | N19: =IF(K19>=M19,"TRUE","FALSE") -> FALSE | O19: =IFERROR(K19/M19,0) -> 0.65014589 | P19: =IF(AND(L19>=0,Q19>=6,K19>=M19*0.25),"TRUE","FALSE") -> TRUE | Q19: =IFERROR(L19/(input!B7),0) -> 16.574667 | R19: baseline
A20: SCN000 | B20: Baseline | C20: 18 | D20: 18 | E20: =input!B5+18 -> 56 | F20: =input!B6*12 -> 57600 | G20: =input!B7*12 -> 36000 | H20: =F20-G20 -> 21600 | I20: =input!B11*12+MAX(0, MIN(input!B18, H20/12)) * 12 -> 33096 | J20: =K19 -> 1625299.7 | K20: =J20*(1+input!B14)+I20*((1+input!B14)-1)/input!B14 -> 1772166.7 | L20: =L19+MAX(0,H20/12) -> 51524 | M20: =calc_metrics!B4 -> 2499900 | N20: =IF(K20>=M20,"TRUE","FALSE") -> FALSE | O20: =IFERROR(K20/M20,0) -> 0.70889504 | P20: =IF(AND(L20>=0,Q20>=6,K20>=M20*0.25),"TRUE","FALSE") -> TRUE | Q20: =IFERROR(L20/(input!B7),0) -> 17.174667 | R20: baseline
A21: SCN000 | B21: Baseline | C21: 19 | D21: 19 | E21: =input!B5+19 -> 57 | F21: =input!B6*12 -> 57600 | G21: =input!B7*12 -> 36000 | H21: =F21-G21 -> 21600 | I21: =input!B11*12+MAX(0, MIN(input!B18, H21/12)) * 12 -> 33096 | J21: =K20 -> 1772166.7 | K21: =J21*(1+input!B14)+I21*((1+input!B14)-1)/input!B14 -> 1929314.4 | L21: =L20+MAX(0,H21/12) -> 53324 | M21: =calc_metrics!B4 -> 2499900 | N21: =IF(K21>=M21,"TRUE","FALSE") -> FALSE | O21: =IFERROR(K21/M21,0) -> 0.77175662 | P21: =IF(AND(L21>=0,Q21>=6,K21>=M21*0.25),"TRUE","FALSE") -> TRUE | Q21: =IFERROR(L21/(input!B7),0) -> 17.774667 | R21: baseline
A22: SCN000 | B22: Baseline | C22: 20 | D22: 20 | E22: =input!B5+20 -> 58 | F22: =input!B6*12 -> 57600 | G22: =input!B7*12 -> 36000 | H22: =F22-G22 -> 21600 | I22: =input!B11*12+MAX(0, MIN(input!B18, H22/12)) * 12 -> 33096 | J22: =K21 -> 1929314.4 | K22: =J22*(1+input!B14)+I22*((1+input!B14)-1)/input!B14 -> 2097462.4 | L22: =L21+MAX(0,H22/12) -> 55124 | M22: =calc_metrics!B4 -> 2499900 | N22: =IF(K22>=M22,"TRUE","FALSE") -> FALSE | O22: =IFERROR(K22/M22,0) -> 0.83901851 | P22: =IF(AND(L22>=0,Q22>=6,K22>=M22*0.25),"TRUE","FALSE") -> TRUE | Q22: =IFERROR(L22/(input!B7),0) -> 18.374667 | R22: baseline
A23: SCN000 | B23: Baseline | C23: 21 | D23: 21 | E23: =input!B5+21 -> 59 | F23: =input!B6*12 -> 57600 | G23: =input!B7*12 -> 36000 | H23: =F23-G23 -> 21600 | I23: =input!B11*12+MAX(0, MIN(input!B18, H23/12)) * 12 -> 33096 | J23: =K22 -> 2097462.4 | K23: =J23*(1+input!B14)+I23*((1+input!B14)-1)/input!B14 -> 2277380.7 | L23: =L22+MAX(0,H23/12) -> 56924 | M23: =calc_metrics!B4 -> 2499900 | N23: =IF(K23>=M23,"TRUE","FALSE") -> FALSE | O23: =IFERROR(K23/M23,0) -> 0.91098874 | P23: =IF(AND(L23>=0,Q23>=6,K23>=M23*0.25),"TRUE","FALSE") -> TRUE | Q23: =IFERROR(L23/(input!B7),0) -> 18.974667 | R23: baseline
A24: SCN000 | B24: Baseline | C24: 22 | D24: 22 | E24: =input!B5+22 -> 60 | F24: =input!B6*12 -> 57600 | G24: =input!B7*12 -> 36000 | H24: =F24-G24 -> 21600 | I24: =input!B11*12+MAX(0, MIN(input!B18, H24/12)) * 12 -> 33096 | J24: =K23 -> 2277380.7 | K24: =J24*(1+input!B14)+I24*((1+input!B14)-1)/input!B14 -> 2469893.4 | L24: =L23+MAX(0,H24/12) -> 58724 | M24: =calc_metrics!B4 -> 2499900 | N24: =IF(K24>=M24,"TRUE","FALSE") -> FALSE | O24: =IFERROR(K24/M24,0) -> 0.98799688 | P24: =IF(AND(L24>=0,Q24>=6,K24>=M24*0.25),"TRUE","FALSE") -> TRUE | Q24: =IFERROR(L24/(input!B7),0) -> 19.574667 | R24: baseline
A25: SCN000 | B25: Baseline | C25: 23 | D25: 23 | E25: =input!B5+23 -> 61 | F25: =input!B6*12 -> 57600 | G25: =input!B7*12 -> 36000 | H25: =F25-G25 -> 21600 | I25: =input!B11*12+MAX(0, MIN(input!B18, H25/12)) * 12 -> 33096 | J25: =K24 -> 2469893.4 | K25: =J25*(1+input!B14)+I25*((1+input!B14)-1)/input!B14 -> 2675881.9 | L25: =L24+MAX(0,H25/12) -> 60524 | M25: =calc_metrics!B4 -> 2499900 | N25: =IF(K25>=M25,"TRUE","FALSE") -> TRUE | O25: =IFERROR(K25/M25,0) -> 1.0703956 | P25: =IF(AND(L25>=0,Q25>=6,K25>=M25*0.25),"TRUE","FALSE") -> TRUE | Q25: =IFERROR(L25/(input!B7),0) -> 20.174667 | R25: baseline
A26: SCN000 | B26: Baseline | C26: 24 | D26: 24 | E26: =input!B5+24 -> 62 | F26: =input!B6*12 -> 57600 | G26: =input!B7*12 -> 36000 | H26: =F26-G26 -> 21600 | I26: =input!B11*12+MAX(0, MIN(input!B18, H26/12)) * 12 -> 33096 | J26: =K25 -> 2675881.9 | K26: =J26*(1+input!B14)+I26*((1+input!B14)-1)/input!B14 -> 2896289.7 | L26: =L25+MAX(0,H26/12) -> 62324 | M26: =calc_metrics!B4 -> 2499900 | N26: =IF(K26>=M26,"TRUE","FALSE") -> TRUE | O26: =IFERROR(K26/M26,0) -> 1.1585622 | P26: =IF(AND(L26>=0,Q26>=6,K26>=M26*0.25),"TRUE","FALSE") -> TRUE | Q26: =IFERROR(L26/(input!B7),0) -> 20.774667 | R26: baseline
A27: SCN000 | B27: Baseline | C27: 25 | D27: 25 | E27: =input!B5+25 -> 63 | F27: =input!B6*12 -> 57600 | G27: =input!B7*12 -> 36000 | H27: =F27-G27 -> 21600 | I27: =input!B11*12+MAX(0, MIN(input!B18, H27/12)) * 12 -> 33096 | J27: =K26 -> 2896289.7 | K27: =J27*(1+input!B14)+I27*((1+input!B14)-1)/input!B14 -> 3132125.9 | L27: =L26+MAX(0,H27/12) -> 64124 | M27: =calc_metrics!B4 -> 2499900 | N27: =IF(K27>=M27,"TRUE","FALSE") -> TRUE | O27: =IFERROR(K27/M27,0) -> 1.2529005 | P27: =IF(AND(L27>=0,Q27>=6,K27>=M27*0.25),"TRUE","FALSE") -> TRUE | Q27: =IFERROR(L27/(input!B7),0) -> 21.374667 | R27: baseline
A28: SCN000 | B28: Baseline | C28: 26 | D28: 26 | E28: =input!B5+26 -> 64 | F28: =input!B6*12 -> 57600 | G28: =input!B7*12 -> 36000 | H28: =F28-G28 -> 21600 | I28: =input!B11*12+MAX(0, MIN(input!B18, H28/12)) * 12 -> 33096 | J28: =K27 -> 3132125.9 | K28: =J28*(1+input!B14)+I28*((1+input!B14)-1)/input!B14 -> 3384470.8 | L28: =L27+MAX(0,H28/12) -> 65924 | M28: =calc_metrics!B4 -> 2499900 | N28: =IF(K28>=M28,"TRUE","FALSE") -> TRUE | O28: =IFERROR(K28/M28,0) -> 1.3538425 | P28: =IF(AND(L28>=0,Q28>=6,K28>=M28*0.25),"TRUE","FALSE") -> TRUE | Q28: =IFERROR(L28/(input!B7),0) -> 21.974667 | R28: baseline
A29: SCN000 | B29: Baseline | C29: 27 | D29: 27 | E29: =input!B5+27 -> 65 | F29: =input!B6*12 -> 57600 | G29: =input!B7*12 -> 36000 | H29: =F29-G29 -> 21600 | I29: =input!B11*12+MAX(0, MIN(input!B18, H29/12)) * 12 -> 33096 | J29: =K28 -> 3384470.8 | K29: =J29*(1+input!B14)+I29*((1+input!B14)-1)/input!B14 -> 3654479.7 | L29: =L28+MAX(0,H29/12) -> 67724 | M29: =calc_metrics!B4 -> 2499900 | N29: =IF(K29>=M29,"TRUE","FALSE") -> TRUE | O29: =IFERROR(K29/M29,0) -> 1.4618504 | P29: =IF(AND(L29>=0,Q29>=6,K29>=M29*0.25),"TRUE","FALSE") -> TRUE | Q29: =IFERROR(L29/(input!B7),0) -> 22.574667 | R29: baseline
A30: SCN000 | B30: Baseline | C30: 28 | D30: 28 | E30: =input!B5+28 -> 66 | F30: =input!B6*12 -> 57600 | G30: =input!B7*12 -> 36000 | H30: =F30-G30 -> 21600 | I30: =input!B11*12+MAX(0, MIN(input!B18, H30/12)) * 12 -> 33096 | J30: =K29 -> 3654479.7 | K30: =J30*(1+input!B14)+I30*((1+input!B14)-1)/input!B14 -> 3943389.3 | L30: =L29+MAX(0,H30/12) -> 69524 | M30: =calc_metrics!B4 -> 2499900 | N30: =IF(K30>=M30,"TRUE","FALSE") -> TRUE | O30: =IFERROR(K30/M30,0) -> 1.5774188 | P30: =IF(AND(L30>=0,Q30>=6,K30>=M30*0.25),"TRUE","FALSE") -> TRUE | Q30: =IFERROR(L30/(input!B7),0) -> 23.174667 | R30: baseline
A31: SCN000 | B31: Baseline | C31: 29 | D31: 29 | E31: =input!B5+29 -> 67 | F31: =input!B6*12 -> 57600 | G31: =input!B7*12 -> 36000 | H31: =F31-G31 -> 21600 | I31: =input!B11*12+MAX(0, MIN(input!B18, H31/12)) * 12 -> 33096 | J31: =K30 -> 3943389.3 | K31: =J31*(1+input!B14)+I31*((1+input!B14)-1)/input!B14 -> 4252522.5 | L31: =L30+MAX(0,H31/12) -> 71324 | M31: =calc_metrics!B4 -> 2499900 | N31: =IF(K31>=M31,"TRUE","FALSE") -> TRUE | O31: =IFERROR(K31/M31,0) -> 1.7010771 | P31: =IF(AND(L31>=0,Q31>=6,K31>=M31*0.25),"TRUE","FALSE") -> TRUE | Q31: =IFERROR(L31/(input!B7),0) -> 23.774667 | R31: baseline
A32: SCN000 | B32: Baseline | C32: 30 | D32: 30 | E32: =input!B5+30 -> 68 | F32: =input!B6*12 -> 57600 | G32: =input!B7*12 -> 36000 | H32: =F32-G32 -> 21600 | I32: =input!B11*12+MAX(0, MIN(input!B18, H32/12)) * 12 -> 33096 | J32: =K31 -> 4252522.5 | K32: =J32*(1+input!B14)+I32*((1+input!B14)-1)/input!B14 -> 4583295.1 | L32: =L31+MAX(0,H32/12) -> 73124 | M32: =calc_metrics!B4 -> 2499900 | N32: =IF(K32>=M32,"TRUE","FALSE") -> TRUE | O32: =IFERROR(K32/M32,0) -> 1.8333914 | P32: =IF(AND(L32>=0,Q32>=6,K32>=M32*0.25),"TRUE","FALSE") -> TRUE | Q32: =IFERROR(L32/(input!B7),0) -> 24.374667 | R32: baseline
A33: SCN000 | B33: Baseline | C33: 31 | D33: 31 | E33: =input!B5+31 -> 69 | F33: =input!B6*12 -> 57600 | G33: =input!B7*12 -> 36000 | H33: =F33-G33 -> 21600 | I33: =input!B11*12+MAX(0, MIN(input!B18, H33/12)) * 12 -> 33096 | J33: =K32 -> 4583295.1 | K33: =J33*(1+input!B14)+I33*((1+input!B14)-1)/input!B14 -> 4937221.8 | L33: =L32+MAX(0,H33/12) -> 74924 | M33: =calc_metrics!B4 -> 2499900 | N33: =IF(K33>=M33,"TRUE","FALSE") -> TRUE | O33: =IFERROR(K33/M33,0) -> 1.9749677 | P33: =IF(AND(L33>=0,Q33>=6,K33>=M33*0.25),"TRUE","FALSE") -> TRUE | Q33: =IFERROR(L33/(input!B7),0) -> 24.974667 | R33: baseline
A34: SCN000 | B34: Baseline | C34: 32 | D34: 32 | E34: =input!B5+32 -> 70 | F34: =input!B6*12 -> 57600 | G34: =input!B7*12 -> 36000 | H34: =F34-G34 -> 21600 | I34: =input!B11*12+MAX(0, MIN(input!B18, H34/12)) * 12 -> 33096 | J34: =K33 -> 4937221.8 | K34: =J34*(1+input!B14)+I34*((1+input!B14)-1)/input!B14 -> 5315923.3 | L34: =L33+MAX(0,H34/12) -> 76724 | M34: =calc_metrics!B4 -> 2499900 | N34: =IF(K34>=M34,"TRUE","FALSE") -> TRUE | O34: =IFERROR(K34/M34,0) -> 2.1264544 | P34: =IF(AND(L34>=0,Q34>=6,K34>=M34*0.25),"TRUE","FALSE") -> TRUE | Q34: =IFERROR(L34/(input!B7),0) -> 25.574667 | R34: baseline
A35: SCN000 | B35: Baseline | C35: 33 | D35: 33 | E35: =input!B5+33 -> 71 | F35: =input!B6*12 -> 57600 | G35: =input!B7*12 -> 36000 | H35: =F35-G35 -> 21600 | I35: =input!B11*12+MAX(0, MIN(input!B18, H35/12)) * 12 -> 33096 | J35: =K34 -> 5315923.3 | K35: =J35*(1+input!B14)+I35*((1+input!B14)-1)/input!B14 -> 5721133.9 | L35: =L34+MAX(0,H35/12) -> 78524 | M35: =calc_metrics!B4 -> 2499900 | N35: =IF(K35>=M35,"TRUE","FALSE") -> TRUE | O35: =IFERROR(K35/M35,0) -> 2.2885451 | P35: =IF(AND(L35>=0,Q35>=6,K35>=M35*0.25),"TRUE","FALSE") -> TRUE | Q35: =IFERROR(L35/(input!B7),0) -> 26.174667 | R35: baseline
A36: SCN000 | B36: Baseline | C36: 34 | D36: 34 | E36: =input!B5+34 -> 72 | F36: =input!B6*12 -> 57600 | G36: =input!B7*12 -> 36000 | H36: =F36-G36 -> 21600 | I36: =input!B11*12+MAX(0, MIN(input!B18, H36/12)) * 12 -> 33096 | J36: =K35 -> 5721133.9 | K36: =J36*(1+input!B14)+I36*((1+input!B14)-1)/input!B14 -> 6154709.3 | L36: =L35+MAX(0,H36/12) -> 80324 | M36: =calc_metrics!B4 -> 2499900 | N36: =IF(K36>=M36,"TRUE","FALSE") -> TRUE | O36: =IFERROR(K36/M36,0) -> 2.4619822 | P36: =IF(AND(L36>=0,Q36>=6,K36>=M36*0.25),"TRUE","FALSE") -> TRUE | Q36: =IFERROR(L36/(input!B7),0) -> 26.774667 | R36: baseline
A37: SCN000 | B37: Baseline | C37: 35 | D37: 35 | E37: =input!B5+35 -> 73 | F37: =input!B6*12 -> 57600 | G37: =input!B7*12 -> 36000 | H37: =F37-G37 -> 21600 | I37: =input!B11*12+MAX(0, MIN(input!B18, H37/12)) * 12 -> 33096 | J37: =K36 -> 6154709.3 | K37: =J37*(1+input!B14)+I37*((1+input!B14)-1)/input!B14 -> 6618635 | L37: =L36+MAX(0,H37/12) -> 82124 | M37: =calc_metrics!B4 -> 2499900 | N37: =IF(K37>=M37,"TRUE","FALSE") -> TRUE | O37: =IFERROR(K37/M37,0) -> 2.6475599 | P37: =IF(AND(L37>=0,Q37>=6,K37>=M37*0.25),"TRUE","FALSE") -> TRUE | Q37: =IFERROR(L37/(input!B7),0) -> 27.374667 | R37: baseline
A38: SCN000 | B38: Baseline | C38: 36 | D38: 36 | E38: =input!B5+36 -> 74 | F38: =input!B6*12 -> 57600 | G38: =input!B7*12 -> 36000 | H38: =F38-G38 -> 21600 | I38: =input!B11*12+MAX(0, MIN(input!B18, H38/12)) * 12 -> 33096 | J38: =K37 -> 6618635 | K38: =J38*(1+input!B14)+I38*((1+input!B14)-1)/input!B14 -> 7115035.4 | L38: =L37+MAX(0,H38/12) -> 83924 | M38: =calc_metrics!B4 -> 2499900 | N38: =IF(K38>=M38,"TRUE","FALSE") -> TRUE | O38: =IFERROR(K38/M38,0) -> 2.846128 | P38: =IF(AND(L38>=0,Q38>=6,K38>=M38*0.25),"TRUE","FALSE") -> TRUE | Q38: =IFERROR(L38/(input!B7),0) -> 27.974667 | R38: baseline
A39: SCN000 | B39: Baseline | C39: 37 | D39: 37 | E39: =input!B5+37 -> 75 | F39: =input!B6*12 -> 57600 | G39: =input!B7*12 -> 36000 | H39: =F39-G39 -> 21600 | I39: =input!B11*12+MAX(0, MIN(input!B18, H39/12)) * 12 -> 33096 | J39: =K38 -> 7115035.4 | K39: =J39*(1+input!B14)+I39*((1+input!B14)-1)/input!B14 -> 7646183.9 | L39: =L38+MAX(0,H39/12) -> 85724 | M39: =calc_metrics!B4 -> 2499900 | N39: =IF(K39>=M39,"TRUE","FALSE") -> TRUE | O39: =IFERROR(K39/M39,0) -> 3.0585959 | P39: =IF(AND(L39>=0,Q39>=6,K39>=M39*0.25),"TRUE","FALSE") -> TRUE | Q39: =IFERROR(L39/(input!B7),0) -> 28.574667 | R39: baseline
A40: SCN000 | B40: Baseline | C40: 38 | D40: 38 | E40: =input!B5+38 -> 76 | F40: =input!B6*12 -> 57600 | G40: =input!B7*12 -> 36000 | H40: =F40-G40 -> 21600 | I40: =input!B11*12+MAX(0, MIN(input!B18, H40/12)) * 12 -> 33096 | J40: =K39 -> 7646183.9 | K40: =J40*(1+input!B14)+I40*((1+input!B14)-1)/input!B14 -> 8214512.8 | L40: =L39+MAX(0,H40/12) -> 87524 | M40: =calc_metrics!B4 -> 2499900 | N40: =IF(K40>=M40,"TRUE","FALSE") -> TRUE | O40: =IFERROR(K40/M40,0) -> 3.2859365 | P40: =IF(AND(L40>=0,Q40>=6,K40>=M40*0.25),"TRUE","FALSE") -> TRUE | Q40: =IFERROR(L40/(input!B7),0) -> 29.174667 | R40: baseline
A41: SCN000 | B41: Baseline | C41: 39 | D41: 39 | E41: =input!B5+39 -> 77 | F41: =input!B6*12 -> 57600 | G41: =input!B7*12 -> 36000 | H41: =F41-G41 -> 21600 | I41: =input!B11*12+MAX(0, MIN(input!B18, H41/12)) * 12 -> 33096 | J41: =K40 -> 8214512.8 | K41: =J41*(1+input!B14)+I41*((1+input!B14)-1)/input!B14 -> 8822624.7 | L41: =L40+MAX(0,H41/12) -> 89324 | M41: =calc_metrics!B4 -> 2499900 | N41: =IF(K41>=M41,"TRUE","FALSE") -> TRUE | O41: =IFERROR(K41/M41,0) -> 3.529191 | P41: =IF(AND(L41>=0,Q41>=6,K41>=M41*0.25),"TRUE","FALSE") -> TRUE | Q41: =IFERROR(L41/(input!B7),0) -> 29.774667 | R41: baseline
A42: SCN001 | B42: Career Break 1yr | C42: 0 | D42: 0 | E42: =input!B5+0 -> 38 | F42: =input!B6*12 -> 57600 | G42: =input!B7*12 -> 36000 | H42: =F42-G42 -> 21600 | I42: =input!B11*12+MAX(0, MIN(input!B18, H42/12)) * 12 -> 33096 | J42: =calc_is!B13 -> 147952 | K42: =J42*(1+input!B14)+I42*((1+input!B14)-1)/input!B14 -> 191404.64 | L42: =input!B8 -> 19124 | M42: =calc_metrics!B4 -> 2499900 | N42: =IF(K42>=M42,"TRUE","FALSE") -> FALSE | O42: =IFERROR(K42/M42,0) -> 0.076564919 | P42: =IF(AND(L42>=0,Q42>=6,K42>=M42*0.25),"TRUE","FALSE") -> FALSE | Q42: =IFERROR(L42/(input!B7),0) -> 6.3746667 | R42: flow_shock
A43: SCN001 | B43: Career Break 1yr | C43: 1 | D43: 1 | E43: =input!B5+1 -> 39 | F43: =input!B6*12*(1+input!G29) -> 0 | G43: =( input!B7 + input!I29 ) * 12 -> 36000 | H43: =F43-G43 -> -36000 | I43: =0+MAX(0, MIN(input!B18+input!J29, H43/12)) * 12 -> 0 | J43: =K42 -> 191404.64 | K43: =J43*(1+input!B14)+I43*((1+input!B14)-1)/input!B14 -> 204802.96 | L43: =L42+MAX(0,H43/12) -> 19124 | M43: =calc_metrics!B4 -> 2499900 | N43: =IF(K43>=M43,"TRUE","FALSE") -> FALSE | O43: =IFERROR(K43/M43,0) -> 0.081924463 | P43: =IF(AND(L43>=0,Q43>=6,K43>=M43*0.25),"TRUE","FALSE") -> FALSE | Q43: =IFERROR(L43/(input!B7),0) -> 6.3746667 | R43: flow_shock
A44: SCN001 | B44: Career Break 1yr | C44: 2 | D44: 2 | E44: =input!B5+2 -> 40 | F44: =input!B6*12 -> 57600 | G44: =input!B7*12 -> 36000 | H44: =F44-G44 -> 21600 | I44: =input!B11*12+MAX(0, MIN(input!B18, H44/12)) * 12 -> 33096 | J44: =K43 -> 204802.96 | K44: =J44*(1+input!B14)+I44*((1+input!B14)-1)/input!B14 -> 252235.17 | L44: =L43+MAX(0,H44/12) -> 20924 | M44: =calc_metrics!B4 -> 2499900 | N44: =IF(K44>=M44,"TRUE","FALSE") -> FALSE | O44: =IFERROR(K44/M44,0) -> 0.1008981 | P44: =IF(AND(L44>=0,Q44>=6,K44>=M44*0.25),"TRUE","FALSE") -> FALSE | Q44: =IFERROR(L44/(input!B7),0) -> 6.9746667 | R44: flow_shock
A45: SCN001 | B45: Career Break 1yr | C45: 3 | D45: 3 | E45: =input!B5+3 -> 41 | F45: =input!B6*12 -> 57600 | G45: =input!B7*12 -> 36000 | H45: =F45-G45 -> 21600 | I45: =input!B11*12+MAX(0, MIN(input!B18, H45/12)) * 12 -> 33096 | J45: =K44 -> 252235.17 | K45: =J45*(1+input!B14)+I45*((1+input!B14)-1)/input!B14 -> 302987.63 | L45: =L44+MAX(0,H45/12) -> 22724 | M45: =calc_metrics!B4 -> 2499900 | N45: =IF(K45>=M45,"TRUE","FALSE") -> FALSE | O45: =IFERROR(K45/M45,0) -> 0.1211999 | P45: =IF(AND(L45>=0,Q45>=6,K45>=M45*0.25),"TRUE","FALSE") -> FALSE | Q45: =IFERROR(L45/(input!B7),0) -> 7.5746667 | R45: flow_shock
A46: SCN001 | B46: Career Break 1yr | C46: 4 | D46: 4 | E46: =input!B5+4 -> 42 | F46: =input!B6*12 -> 57600 | G46: =input!B7*12 -> 36000 | H46: =F46-G46 -> 21600 | I46: =input!B11*12+MAX(0, MIN(input!B18, H46/12)) * 12 -> 33096 | J46: =K45 -> 302987.63 | K46: =J46*(1+input!B14)+I46*((1+input!B14)-1)/input!B14 -> 357292.77 | L46: =L45+MAX(0,H46/12) -> 24524 | M46: =calc_metrics!B4 -> 2499900 | N46: =IF(K46>=M46,"TRUE","FALSE") -> FALSE | O46: =IFERROR(K46/M46,0) -> 0.14292282 | P46: =IF(AND(L46>=0,Q46>=6,K46>=M46*0.25),"TRUE","FALSE") -> FALSE | Q46: =IFERROR(L46/(input!B7),0) -> 8.1746667 | R46: flow_shock
A47: SCN001 | B47: Career Break 1yr | C47: 5 | D47: 5 | E47: =input!B5+5 -> 43 | F47: =input!B6*12 -> 57600 | G47: =input!B7*12 -> 36000 | H47: =F47-G47 -> 21600 | I47: =input!B11*12+MAX(0, MIN(input!B18, H47/12)) * 12 -> 33096 | J47: =K46 -> 357292.77 | K47: =J47*(1+input!B14)+I47*((1+input!B14)-1)/input!B14 -> 415399.26 | L47: =L46+MAX(0,H47/12) -> 26324 | M47: =calc_metrics!B4 -> 2499900 | N47: =IF(K47>=M47,"TRUE","FALSE") -> FALSE | O47: =IFERROR(K47/M47,0) -> 0.16616635 | P47: =IF(AND(L47>=0,Q47>=6,K47>=M47*0.25),"TRUE","FALSE") -> FALSE | Q47: =IFERROR(L47/(input!B7),0) -> 8.7746667 | R47: flow_shock
A48: SCN001 | B48: Career Break 1yr | C48: 6 | D48: 6 | E48: =input!B5+6 -> 44 | F48: =input!B6*12 -> 57600 | G48: =input!B7*12 -> 36000 | H48: =F48-G48 -> 21600 | I48: =input!B11*12+MAX(0, MIN(input!B18, H48/12)) * 12 -> 33096 | J48: =K47 -> 415399.26 | K48: =J48*(1+input!B14)+I48*((1+input!B14)-1)/input!B14 -> 477573.21 | L48: =L47+MAX(0,H48/12) -> 28124 | M48: =calc_metrics!B4 -> 2499900 | N48: =IF(K48>=M48,"TRUE","FALSE") -> FALSE | O48: =IFERROR(K48/M48,0) -> 0.19103693 | P48: =IF(AND(L48>=0,Q48>=6,K48>=M48*0.25),"TRUE","FALSE") -> FALSE | Q48: =IFERROR(L48/(input!B7),0) -> 9.3746667 | R48: flow_shock
A49: SCN001 | B49: Career Break 1yr | C49: 7 | D49: 7 | E49: =input!B5+7 -> 45 | F49: =input!B6*12 -> 57600 | G49: =input!B7*12 -> 36000 | H49: =F49-G49 -> 21600 | I49: =input!B11*12+MAX(0, MIN(input!B18, H49/12)) * 12 -> 33096 | J49: =K48 -> 477573.21 | K49: =J49*(1+input!B14)+I49*((1+input!B14)-1)/input!B14 -> 544099.34 | L49: =L48+MAX(0,H49/12) -> 29924 | M49: =calc_metrics!B4 -> 2499900 | N49: =IF(K49>=M49,"TRUE","FALSE") -> FALSE | O49: =IFERROR(K49/M49,0) -> 0.21764844 | P49: =IF(AND(L49>=0,Q49>=6,K49>=M49*0.25),"TRUE","FALSE") -> FALSE | Q49: =IFERROR(L49/(input!B7),0) -> 9.9746667 | R49: flow_shock
A50: SCN001 | B50: Career Break 1yr | C50: 8 | D50: 8 | E50: =input!B5+8 -> 46 | F50: =input!B6*12 -> 57600 | G50: =input!B7*12 -> 36000 | H50: =F50-G50 -> 21600 | I50: =input!B11*12+MAX(0, MIN(input!B18, H50/12)) * 12 -> 33096 | J50: =K49 -> 544099.34 | K50: =J50*(1+input!B14)+I50*((1+input!B14)-1)/input!B14 -> 615282.29 | L50: =L49+MAX(0,H50/12) -> 31724 | M50: =calc_metrics!B4 -> 2499900 | N50: =IF(K50>=M50,"TRUE","FALSE") -> FALSE | O50: =IFERROR(K50/M50,0) -> 0.24612276 | P50: =IF(AND(L50>=0,Q50>=6,K50>=M50*0.25),"TRUE","FALSE") -> FALSE | Q50: =IFERROR(L50/(input!B7),0) -> 10.574667 | R50: flow_shock
A51: SCN001 | B51: Career Break 1yr | C51: 9 | D51: 9 | E51: =input!B5+9 -> 47 | F51: =input!B6*12 -> 57600 | G51: =input!B7*12 -> 36000 | H51: =F51-G51 -> 21600 | I51: =input!B11*12+MAX(0, MIN(input!B18, H51/12)) * 12 -> 33096 | J51: =K50 -> 615282.29 | K51: =J51*(1+input!B14)+I51*((1+input!B14)-1)/input!B14 -> 691448.05 | L51: =L50+MAX(0,H51/12) -> 33524 | M51: =calc_metrics!B4 -> 2499900 | N51: =IF(K51>=M51,"TRUE","FALSE") -> FALSE | O51: =IFERROR(K51/M51,0) -> 0.27659028 | P51: =IF(AND(L51>=0,Q51>=6,K51>=M51*0.25),"TRUE","FALSE") -> TRUE | Q51: =IFERROR(L51/(input!B7),0) -> 11.174667 | R51: flow_shock
A52: SCN001 | B52: Career Break 1yr | C52: 10 | D52: 10 | E52: =input!B5+10 -> 48 | F52: =input!B6*12 -> 57600 | G52: =input!B7*12 -> 36000 | H52: =F52-G52 -> 21600 | I52: =input!B11*12+MAX(0, MIN(input!B18, H52/12)) * 12 -> 33096 | J52: =K51 -> 691448.05 | K52: =J52*(1+input!B14)+I52*((1+input!B14)-1)/input!B14 -> 772945.41 | L52: =L51+MAX(0,H52/12) -> 35324 | M52: =calc_metrics!B4 -> 2499900 | N52: =IF(K52>=M52,"TRUE","FALSE") -> FALSE | O52: =IFERROR(K52/M52,0) -> 0.30919053 | P52: =IF(AND(L52>=0,Q52>=6,K52>=M52*0.25),"TRUE","FALSE") -> TRUE | Q52: =IFERROR(L52/(input!B7),0) -> 11.774667 | R52: flow_shock
A53: SCN001 | B53: Career Break 1yr | C53: 11 | D53: 11 | E53: =input!B5+11 -> 49 | F53: =input!B6*12 -> 57600 | G53: =input!B7*12 -> 36000 | H53: =F53-G53 -> 21600 | I53: =input!B11*12+MAX(0, MIN(input!B18, H53/12)) * 12 -> 33096 | J53: =K52 -> 772945.41 | K53: =J53*(1+input!B14)+I53*((1+input!B14)-1)/input!B14 -> 860147.59 | L53: =L52+MAX(0,H53/12) -> 37124 | M53: =calc_metrics!B4 -> 2499900 | N53: =IF(K53>=M53,"TRUE","FALSE") -> FALSE | O53: =IFERROR(K53/M53,0) -> 0.3440728 | P53: =IF(AND(L53>=0,Q53>=6,K53>=M53*0.25),"TRUE","FALSE") -> TRUE | Q53: =IFERROR(L53/(input!B7),0) -> 12.374667 | R53: flow_shock
A54: SCN001 | B54: Career Break 1yr | C54: 12 | D54: 12 | E54: =input!B5+12 -> 50 | F54: =input!B6*12 -> 57600 | G54: =input!B7*12 -> 36000 | H54: =F54-G54 -> 21600 | I54: =input!B11*12+MAX(0, MIN(input!B18, H54/12)) * 12 -> 33096 | J54: =K53 -> 860147.59 | K54: =J54*(1+input!B14)+I54*((1+input!B14)-1)/input!B14 -> 953453.92 | L54: =L53+MAX(0,H54/12) -> 38924 | M54: =calc_metrics!B4 -> 2499900 | N54: =IF(K54>=M54,"TRUE","FALSE") -> FALSE | O54: =IFERROR(K54/M54,0) -> 0.38139683 | P54: =IF(AND(L54>=0,Q54>=6,K54>=M54*0.25),"TRUE","FALSE") -> TRUE | Q54: =IFERROR(L54/(input!B7),0) -> 12.974667 | R54: flow_shock
A55: SCN001 | B55: Career Break 1yr | C55: 13 | D55: 13 | E55: =input!B5+13 -> 51 | F55: =input!B6*12 -> 57600 | G55: =input!B7*12 -> 36000 | H55: =F55-G55 -> 21600 | I55: =input!B11*12+MAX(0, MIN(input!B18, H55/12)) * 12 -> 33096 | J55: =K54 -> 953453.92 | K55: =J55*(1+input!B14)+I55*((1+input!B14)-1)/input!B14 -> 1053291.7 | L55: =L54+MAX(0,H55/12) -> 40724 | M55: =calc_metrics!B4 -> 2499900 | N55: =IF(K55>=M55,"TRUE","FALSE") -> FALSE | O55: =IFERROR(K55/M55,0) -> 0.42133353 | P55: =IF(AND(L55>=0,Q55>=6,K55>=M55*0.25),"TRUE","FALSE") -> TRUE | Q55: =IFERROR(L55/(input!B7),0) -> 13.574667 | R55: flow_shock
A56: SCN001 | B56: Career Break 1yr | C56: 14 | D56: 14 | E56: =input!B5+14 -> 52 | F56: =input!B6*12 -> 57600 | G56: =input!B7*12 -> 36000 | H56: =F56-G56 -> 21600 | I56: =input!B11*12+MAX(0, MIN(input!B18, H56/12)) * 12 -> 33096 | J56: =K55 -> 1053291.7 | K56: =J56*(1+input!B14)+I56*((1+input!B14)-1)/input!B14 -> 1160118.1 | L56: =L55+MAX(0,H56/12) -> 42524 | M56: =calc_metrics!B4 -> 2499900 | N56: =IF(K56>=M56,"TRUE","FALSE") -> FALSE | O56: =IFERROR(K56/M56,0) -> 0.46406581 | P56: =IF(AND(L56>=0,Q56>=6,K56>=M56*0.25),"TRUE","FALSE") -> TRUE | Q56: =IFERROR(L56/(input!B7),0) -> 14.174667 | R56: flow_shock
A57: SCN001 | B57: Career Break 1yr | C57: 15 | D57: 15 | E57: =input!B5+15 -> 53 | F57: =input!B6*12 -> 57600 | G57: =input!B7*12 -> 36000 | H57: =F57-G57 -> 21600 | I57: =input!B11*12+MAX(0, MIN(input!B18, H57/12)) * 12 -> 33096 | J57: =K56 -> 1160118.1 | K57: =J57*(1+input!B14)+I57*((1+input!B14)-1)/input!B14 -> 1274422.4 | L57: =L56+MAX(0,H57/12) -> 44324 | M57: =calc_metrics!B4 -> 2499900 | N57: =IF(K57>=M57,"TRUE","FALSE") -> FALSE | O57: =IFERROR(K57/M57,0) -> 0.50978935 | P57: =IF(AND(L57>=0,Q57>=6,K57>=M57*0.25),"TRUE","FALSE") -> TRUE | Q57: =IFERROR(L57/(input!B7),0) -> 14.774667 | R57: flow_shock
A58: SCN001 | B58: Career Break 1yr | C58: 16 | D58: 16 | E58: =input!B5+16 -> 54 | F58: =input!B6*12 -> 57600 | G58: =input!B7*12 -> 36000 | H58: =F58-G58 -> 21600 | I58: =input!B11*12+MAX(0, MIN(input!B18, H58/12)) * 12 -> 33096 | J58: =K57 -> 1274422.4 | K58: =J58*(1+input!B14)+I58*((1+input!B14)-1)/input!B14 -> 1396728 | L58: =L57+MAX(0,H58/12) -> 46124 | M58: =calc_metrics!B4 -> 2499900 | N58: =IF(K58>=M58,"TRUE","FALSE") -> FALSE | O58: =IFERROR(K58/M58,0) -> 0.55871353 | P58: =IF(AND(L58>=0,Q58>=6,K58>=M58*0.25),"TRUE","FALSE") -> TRUE | Q58: =IFERROR(L58/(input!B7),0) -> 15.374667 | R58: flow_shock
A59: SCN001 | B59: Career Break 1yr | C59: 17 | D59: 17 | E59: =input!B5+17 -> 55 | F59: =input!B6*12 -> 57600 | G59: =input!B7*12 -> 36000 | H59: =F59-G59 -> 21600 | I59: =input!B11*12+MAX(0, MIN(input!B18, H59/12)) * 12 -> 33096 | J59: =K58 -> 1396728 | K59: =J59*(1+input!B14)+I59*((1+input!B14)-1)/input!B14 -> 1527594.9 | L59: =L58+MAX(0,H59/12) -> 47924 | M59: =calc_metrics!B4 -> 2499900 | N59: =IF(K59>=M59,"TRUE","FALSE") -> FALSE | O59: =IFERROR(K59/M59,0) -> 0.61106241 | P59: =IF(AND(L59>=0,Q59>=6,K59>=M59*0.25),"TRUE","FALSE") -> TRUE | Q59: =IFERROR(L59/(input!B7),0) -> 15.974667 | R59: flow_shock
A60: SCN001 | B60: Career Break 1yr | C60: 18 | D60: 18 | E60: =input!B5+18 -> 56 | F60: =input!B6*12 -> 57600 | G60: =input!B7*12 -> 36000 | H60: =F60-G60 -> 21600 | I60: =input!B11*12+MAX(0, MIN(input!B18, H60/12)) * 12 -> 33096 | J60: =K59 -> 1527594.9 | K60: =J60*(1+input!B14)+I60*((1+input!B14)-1)/input!B14 -> 1667622.6 | L60: =L59+MAX(0,H60/12) -> 49724 | M60: =calc_metrics!B4 -> 2499900 | N60: =IF(K60>=M60,"TRUE","FALSE") -> FALSE | O60: =IFERROR(K60/M60,0) -> 0.6670757 | P60: =IF(AND(L60>=0,Q60>=6,K60>=M60*0.25),"TRUE","FALSE") -> TRUE | Q60: =IFERROR(L60/(input!B7),0) -> 16.574667 | R60: flow_shock
A61: SCN001 | B61: Career Break 1yr | C61: 19 | D61: 19 | E61: =input!B5+19 -> 57 | F61: =input!B6*12 -> 57600 | G61: =input!B7*12 -> 36000 | H61: =F61-G61 -> 21600 | I61: =input!B11*12+MAX(0, MIN(input!B18, H61/12)) * 12 -> 33096 | J61: =K60 -> 1667622.6 | K61: =J61*(1+input!B14)+I61*((1+input!B14)-1)/input!B14 -> 1817452.1 | L61: =L60+MAX(0,H61/12) -> 51524 | M61: =calc_metrics!B4 -> 2499900 | N61: =IF(K61>=M61,"TRUE","FALSE") -> FALSE | O61: =IFERROR(K61/M61,0) -> 0.72700993 | P61: =IF(AND(L61>=0,Q61>=6,K61>=M61*0.25),"TRUE","FALSE") -> TRUE | Q61: =IFERROR(L61/(input!B7),0) -> 17.174667 | R61: flow_shock
A62: SCN001 | B62: Career Break 1yr | C62: 20 | D62: 20 | E62: =input!B5+20 -> 58 | F62: =input!B6*12 -> 57600 | G62: =input!B7*12 -> 36000 | H62: =F62-G62 -> 21600 | I62: =input!B11*12+MAX(0, MIN(input!B18, H62/12)) * 12 -> 33096 | J62: =K61 -> 1817452.1 | K62: =J62*(1+input!B14)+I62*((1+input!B14)-1)/input!B14 -> 1977769.8 | L62: =L61+MAX(0,H62/12) -> 53324 | M62: =calc_metrics!B4 -> 2499900 | N62: =IF(K62>=M62,"TRUE","FALSE") -> FALSE | O62: =IFERROR(K62/M62,0) -> 0.79113956 | P62: =IF(AND(L62>=0,Q62>=6,K62>=M62*0.25),"TRUE","FALSE") -> TRUE | Q62: =IFERROR(L62/(input!B7),0) -> 17.774667 | R62: flow_shock
A63: SCN001 | B63: Career Break 1yr | C63: 21 | D63: 21 | E63: =input!B5+21 -> 59 | F63: =input!B6*12 -> 57600 | G63: =input!B7*12 -> 36000 | H63: =F63-G63 -> 21600 | I63: =input!B11*12+MAX(0, MIN(input!B18, H63/12)) * 12 -> 33096 | J63: =K62 -> 1977769.8 | K63: =J63*(1+input!B14)+I63*((1+input!B14)-1)/input!B14 -> 2149309.7 | L63: =L62+MAX(0,H63/12) -> 55124 | M63: =calc_metrics!B4 -> 2499900 | N63: =IF(K63>=M63,"TRUE","FALSE") -> FALSE | O63: =IFERROR(K63/M63,0) -> 0.85975826 | P63: =IF(AND(L63>=0,Q63>=6,K63>=M63*0.25),"TRUE","FALSE") -> TRUE | Q63: =IFERROR(L63/(input!B7),0) -> 18.374667 | R63: flow_shock
A64: SCN001 | B64: Career Break 1yr | C64: 22 | D64: 22 | E64: =input!B5+22 -> 60 | F64: =input!B6*12 -> 57600 | G64: =input!B7*12 -> 36000 | H64: =F64-G64 -> 21600 | I64: =input!B11*12+MAX(0, MIN(input!B18, H64/12)) * 12 -> 33096 | J64: =K63 -> 2149309.7 | K64: =J64*(1+input!B14)+I64*((1+input!B14)-1)/input!B14 -> 2332857.3 | L64: =L63+MAX(0,H64/12) -> 56924 | M64: =calc_metrics!B4 -> 2499900 | N64: =IF(K64>=M64,"TRUE","FALSE") -> FALSE | O64: =IFERROR(K64/M64,0) -> 0.93318026 | P64: =IF(AND(L64>=0,Q64>=6,K64>=M64*0.25),"TRUE","FALSE") -> TRUE | Q64: =IFERROR(L64/(input!B7),0) -> 18.974667 | R64: flow_shock
A65: SCN001 | B65: Career Break 1yr | C65: 23 | D65: 23 | E65: =input!B5+23 -> 61 | F65: =input!B6*12 -> 57600 | G65: =input!B7*12 -> 36000 | H65: =F65-G65 -> 21600 | I65: =input!B11*12+MAX(0, MIN(input!B18, H65/12)) * 12 -> 33096 | J65: =K64 -> 2332857.3 | K65: =J65*(1+input!B14)+I65*((1+input!B14)-1)/input!B14 -> 2529253.4 | L65: =L64+MAX(0,H65/12) -> 58724 | M65: =calc_metrics!B4 -> 2499900 | N65: =IF(K65>=M65,"TRUE","FALSE") -> TRUE | O65: =IFERROR(K65/M65,0) -> 1.0117418 | P65: =IF(AND(L65>=0,Q65>=6,K65>=M65*0.25),"TRUE","FALSE") -> TRUE | Q65: =IFERROR(L65/(input!B7),0) -> 19.574667 | R65: flow_shock
A66: SCN001 | B66: Career Break 1yr | C66: 24 | D66: 24 | E66: =input!B5+24 -> 62 | F66: =input!B6*12 -> 57600 | G66: =input!B7*12 -> 36000 | H66: =F66-G66 -> 21600 | I66: =input!B11*12+MAX(0, MIN(input!B18, H66/12)) * 12 -> 33096 | J66: =K65 -> 2529253.4 | K66: =J66*(1+input!B14)+I66*((1+input!B14)-1)/input!B14 -> 2739397.1 | L66: =L65+MAX(0,H66/12) -> 60524 | M66: =calc_metrics!B4 -> 2499900 | N66: =IF(K66>=M66,"TRUE","FALSE") -> TRUE | O66: =IFERROR(K66/M66,0) -> 1.0958027 | P66: =IF(AND(L66>=0,Q66>=6,K66>=M66*0.25),"TRUE","FALSE") -> TRUE | Q66: =IFERROR(L66/(input!B7),0) -> 20.174667 | R66: flow_shock
A67: SCN001 | B67: Career Break 1yr | C67: 25 | D67: 25 | E67: =input!B5+25 -> 63 | F67: =input!B6*12 -> 57600 | G67: =input!B7*12 -> 36000 | H67: =F67-G67 -> 21600 | I67: =input!B11*12+MAX(0, MIN(input!B18, H67/12)) * 12 -> 33096 | J67: =K66 -> 2739397.1 | K67: =J67*(1+input!B14)+I67*((1+input!B14)-1)/input!B14 -> 2964250.9 | L67: =L66+MAX(0,H67/12) -> 62324 | M67: =calc_metrics!B4 -> 2499900 | N67: =IF(K67>=M67,"TRUE","FALSE") -> TRUE | O67: =IFERROR(K67/M67,0) -> 1.1857478 | P67: =IF(AND(L67>=0,Q67>=6,K67>=M67*0.25),"TRUE","FALSE") -> TRUE | Q67: =IFERROR(L67/(input!B7),0) -> 20.774667 | R67: flow_shock
A68: SCN001 | B68: Career Break 1yr | C68: 26 | D68: 26 | E68: =input!B5+26 -> 64 | F68: =input!B6*12 -> 57600 | G68: =input!B7*12 -> 36000 | H68: =F68-G68 -> 21600 | I68: =input!B11*12+MAX(0, MIN(input!B18, H68/12)) * 12 -> 33096 | J68: =K67 -> 2964250.9 | K68: =J68*(1+input!B14)+I68*((1+input!B14)-1)/input!B14 -> 3204844.4 | L68: =L67+MAX(0,H68/12) -> 64124 | M68: =calc_metrics!B4 -> 2499900 | N68: =IF(K68>=M68,"TRUE","FALSE") -> TRUE | O68: =IFERROR(K68/M68,0) -> 1.2819891 | P68: =IF(AND(L68>=0,Q68>=6,K68>=M68*0.25),"TRUE","FALSE") -> TRUE | Q68: =IFERROR(L68/(input!B7),0) -> 21.374667 | R68: flow_shock
A69: SCN001 | B69: Career Break 1yr | C69: 27 | D69: 27 | E69: =input!B5+27 -> 65 | F69: =input!B6*12 -> 57600 | G69: =input!B7*12 -> 36000 | H69: =F69-G69 -> 21600 | I69: =input!B11*12+MAX(0, MIN(input!B18, H69/12)) * 12 -> 33096 | J69: =K68 -> 3204844.4 | K69: =J69*(1+input!B14)+I69*((1+input!B14)-1)/input!B14 -> 3462279.6 | L69: =L68+MAX(0,H69/12) -> 65924 | M69: =calc_metrics!B4 -> 2499900 | N69: =IF(K69>=M69,"TRUE","FALSE") -> TRUE | O69: =IFERROR(K69/M69,0) -> 1.3849672 | P69: =IF(AND(L69>=0,Q69>=6,K69>=M69*0.25),"TRUE","FALSE") -> TRUE | Q69: =IFERROR(L69/(input!B7),0) -> 21.974667 | R69: flow_shock
A70: SCN001 | B70: Career Break 1yr | C70: 28 | D70: 28 | E70: =input!B5+28 -> 66 | F70: =input!B6*12 -> 57600 | G70: =input!B7*12 -> 36000 | H70: =F70-G70 -> 21600 | I70: =input!B11*12+MAX(0, MIN(input!B18, H70/12)) * 12 -> 33096 | J70: =K69 -> 3462279.6 | K70: =J70*(1+input!B14)+I70*((1+input!B14)-1)/input!B14 -> 3737735.1 | L70: =L69+MAX(0,H70/12) -> 67724 | M70: =calc_metrics!B4 -> 2499900 | N70: =IF(K70>=M70,"TRUE","FALSE") -> TRUE | O70: =IFERROR(K70/M70,0) -> 1.4951539 | P70: =IF(AND(L70>=0,Q70>=6,K70>=M70*0.25),"TRUE","FALSE") -> TRUE | Q70: =IFERROR(L70/(input!B7),0) -> 22.574667 | R70: flow_shock
A71: SCN001 | B71: Career Break 1yr | C71: 29 | D71: 29 | E71: =input!B5+29 -> 67 | F71: =input!B6*12 -> 57600 | G71: =input!B7*12 -> 36000 | H71: =F71-G71 -> 21600 | I71: =input!B11*12+MAX(0, MIN(input!B18, H71/12)) * 12 -> 33096 | J71: =K70 -> 3737735.1 | K71: =J71*(1+input!B14)+I71*((1+input!B14)-1)/input!B14 -> 4032472.6 | L71: =L70+MAX(0,H71/12) -> 69524 | M71: =calc_metrics!B4 -> 2499900 | N71: =IF(K71>=M71,"TRUE","FALSE") -> TRUE | O71: =IFERROR(K71/M71,0) -> 1.6130536 | P71: =IF(AND(L71>=0,Q71>=6,K71>=M71*0.25),"TRUE","FALSE") -> TRUE | Q71: =IFERROR(L71/(input!B7),0) -> 23.174667 | R71: flow_shock
A72: SCN001 | B72: Career Break 1yr | C72: 30 | D72: 30 | E72: =input!B5+30 -> 68 | F72: =input!B6*12 -> 57600 | G72: =input!B7*12 -> 36000 | H72: =F72-G72 -> 21600 | I72: =input!B11*12+MAX(0, MIN(input!B18, H72/12)) * 12 -> 33096 | J72: =K71 -> 4032472.6 | K72: =J72*(1+input!B14)+I72*((1+input!B14)-1)/input!B14 -> 4347841.7 | L72: =L71+MAX(0,H72/12) -> 71324 | M72: =calc_metrics!B4 -> 2499900 | N72: =IF(K72>=M72,"TRUE","FALSE") -> TRUE | O72: =IFERROR(K72/M72,0) -> 1.7392062 | P72: =IF(AND(L72>=0,Q72>=6,K72>=M72*0.25),"TRUE","FALSE") -> TRUE | Q72: =IFERROR(L72/(input!B7),0) -> 23.774667 | R72: flow_shock
A73: SCN001 | B73: Career Break 1yr | C73: 31 | D73: 31 | E73: =input!B5+31 -> 69 | F73: =input!B6*12 -> 57600 | G73: =input!B7*12 -> 36000 | H73: =F73-G73 -> 21600 | I73: =input!B11*12+MAX(0, MIN(input!B18, H73/12)) * 12 -> 33096 | J73: =K72 -> 4347841.7 | K73: =J73*(1+input!B14)+I73*((1+input!B14)-1)/input!B14 -> 4685286.6 | L73: =L72+MAX(0,H73/12) -> 73124 | M73: =calc_metrics!B4 -> 2499900 | N73: =IF(K73>=M73,"TRUE","FALSE") -> TRUE | O73: =IFERROR(K73/M73,0) -> 1.8741896 | P73: =IF(AND(L73>=0,Q73>=6,K73>=M73*0.25),"TRUE","FALSE") -> TRUE | Q73: =IFERROR(L73/(input!B7),0) -> 24.374667 | R73: flow_shock
A74: SCN001 | B74: Career Break 1yr | C74: 32 | D74: 32 | E74: =input!B5+32 -> 70 | F74: =input!B6*12 -> 57600 | G74: =input!B7*12 -> 36000 | H74: =F74-G74 -> 21600 | I74: =input!B11*12+MAX(0, MIN(input!B18, H74/12)) * 12 -> 33096 | J74: =K73 -> 4685286.6 | K74: =J74*(1+input!B14)+I74*((1+input!B14)-1)/input!B14 -> 5046352.6 | L74: =L73+MAX(0,H74/12) -> 74924 | M74: =calc_metrics!B4 -> 2499900 | N74: =IF(K74>=M74,"TRUE","FALSE") -> TRUE | O74: =IFERROR(K74/M74,0) -> 2.0186218 | P74: =IF(AND(L74>=0,Q74>=6,K74>=M74*0.25),"TRUE","FALSE") -> TRUE | Q74: =IFERROR(L74/(input!B7),0) -> 24.974667 | R74: flow_shock
A75: SCN001 | B75: Career Break 1yr | C75: 33 | D75: 33 | E75: =input!B5+33 -> 71 | F75: =input!B6*12 -> 57600 | G75: =input!B7*12 -> 36000 | H75: =F75-G75 -> 21600 | I75: =input!B11*12+MAX(0, MIN(input!B18, H75/12)) * 12 -> 33096 | J75: =K74 -> 5046352.6 | K75: =J75*(1+input!B14)+I75*((1+input!B14)-1)/input!B14 -> 5432693.3 | L75: =L74+MAX(0,H75/12) -> 76724 | M75: =calc_metrics!B4 -> 2499900 | N75: =IF(K75>=M75,"TRUE","FALSE") -> TRUE | O75: =IFERROR(K75/M75,0) -> 2.1731643 | P75: =IF(AND(L75>=0,Q75>=6,K75>=M75*0.25),"TRUE","FALSE") -> TRUE | Q75: =IFERROR(L75/(input!B7),0) -> 25.574667 | R75: flow_shock
A76: SCN001 | B76: Career Break 1yr | C76: 34 | D76: 34 | E76: =input!B5+34 -> 72 | F76: =input!B6*12 -> 57600 | G76: =input!B7*12 -> 36000 | H76: =F76-G76 -> 21600 | I76: =input!B11*12+MAX(0, MIN(input!B18, H76/12)) * 12 -> 33096 | J76: =K75 -> 5432693.3 | K76: =J76*(1+input!B14)+I76*((1+input!B14)-1)/input!B14 -> 5846077.9 | L76: =L75+MAX(0,H76/12) -> 78524 | M76: =calc_metrics!B4 -> 2499900 | N76: =IF(K76>=M76,"TRUE","FALSE") -> TRUE | O76: =IFERROR(K76/M76,0) -> 2.3385247 | P76: =IF(AND(L76>=0,Q76>=6,K76>=M76*0.25),"TRUE","FALSE") -> TRUE | Q76: =IFERROR(L76/(input!B7),0) -> 26.174667 | R76: flow_shock
A77: SCN001 | B77: Career Break 1yr | C77: 35 | D77: 35 | E77: =input!B5+35 -> 73 | F77: =input!B6*12 -> 57600 | G77: =input!B7*12 -> 36000 | H77: =F77-G77 -> 21600 | I77: =input!B11*12+MAX(0, MIN(input!B18, H77/12)) * 12 -> 33096 | J77: =K76 -> 5846077.9 | K77: =J77*(1+input!B14)+I77*((1+input!B14)-1)/input!B14 -> 6288399.3 | L77: =L76+MAX(0,H77/12) -> 80324 | M77: =calc_metrics!B4 -> 2499900 | N77: =IF(K77>=M77,"TRUE","FALSE") -> TRUE | O77: =IFERROR(K77/M77,0) -> 2.5154603 | P77: =IF(AND(L77>=0,Q77>=6,K77>=M77*0.25),"TRUE","FALSE") -> TRUE | Q77: =IFERROR(L77/(input!B7),0) -> 26.774667 | R77: flow_shock
A78: SCN001 | B78: Career Break 1yr | C78: 36 | D78: 36 | E78: =input!B5+36 -> 74 | F78: =input!B6*12 -> 57600 | G78: =input!B7*12 -> 36000 | H78: =F78-G78 -> 21600 | I78: =input!B11*12+MAX(0, MIN(input!B18, H78/12)) * 12 -> 33096 | J78: =K77 -> 6288399.3 | K78: =J78*(1+input!B14)+I78*((1+input!B14)-1)/input!B14 -> 6761683.3 | L78: =L77+MAX(0,H78/12) -> 82124 | M78: =calc_metrics!B4 -> 2499900 | N78: =IF(K78>=M78,"TRUE","FALSE") -> TRUE | O78: =IFERROR(K78/M78,0) -> 2.7047815 | P78: =IF(AND(L78>=0,Q78>=6,K78>=M78*0.25),"TRUE","FALSE") -> TRUE | Q78: =IFERROR(L78/(input!B7),0) -> 27.374667 | R78: flow_shock
A79: SCN001 | B79: Career Break 1yr | C79: 37 | D79: 37 | E79: =input!B5+37 -> 75 | F79: =input!B6*12 -> 57600 | G79: =input!B7*12 -> 36000 | H79: =F79-G79 -> 21600 | I79: =input!B11*12+MAX(0, MIN(input!B18, H79/12)) * 12 -> 33096 | J79: =K78 -> 6761683.3 | K79: =J79*(1+input!B14)+I79*((1+input!B14)-1)/input!B14 -> 7268097.1 | L79: =L78+MAX(0,H79/12) -> 83924 | M79: =calc_metrics!B4 -> 2499900 | N79: =IF(K79>=M79,"TRUE","FALSE") -> TRUE | O79: =IFERROR(K79/M79,0) -> 2.9073551 | P79: =IF(AND(L79>=0,Q79>=6,K79>=M79*0.25),"TRUE","FALSE") -> TRUE | Q79: =IFERROR(L79/(input!B7),0) -> 27.974667 | R79: flow_shock
A80: SCN001 | B80: Career Break 1yr | C80: 38 | D80: 38 | E80: =input!B5+38 -> 76 | F80: =input!B6*12 -> 57600 | G80: =input!B7*12 -> 36000 | H80: =F80-G80 -> 21600 | I80: =input!B11*12+MAX(0, MIN(input!B18, H80/12)) * 12 -> 33096 | J80: =K79 -> 7268097.1 | K80: =J80*(1+input!B14)+I80*((1+input!B14)-1)/input!B14 -> 7809959.9 | L80: =L79+MAX(0,H80/12) -> 85724 | M80: =calc_metrics!B4 -> 2499900 | N80: =IF(K80>=M80,"TRUE","FALSE") -> TRUE | O80: =IFERROR(K80/M80,0) -> 3.1241089 | P80: =IF(AND(L80>=0,Q80>=6,K80>=M80*0.25),"TRUE","FALSE") -> TRUE | Q80: =IFERROR(L80/(input!B7),0) -> 28.574667 | R80: flow_shock
A81: SCN001 | B81: Career Break 1yr | C81: 39 | D81: 39 | E81: =input!B5+39 -> 77 | F81: =input!B6*12 -> 57600 | G81: =input!B7*12 -> 36000 | H81: =F81-G81 -> 21600 | I81: =input!B11*12+MAX(0, MIN(input!B18, H81/12)) * 12 -> 33096 | J81: =K80 -> 7809959.9 | K81: =J81*(1+input!B14)+I81*((1+input!B14)-1)/input!B14 -> 8389753.1 | L81: =L80+MAX(0,H81/12) -> 87524 | M81: =calc_metrics!B4 -> 2499900 | N81: =IF(K81>=M81,"TRUE","FALSE") -> TRUE | O81: =IFERROR(K81/M81,0) -> 3.3560355 | P81: =IF(AND(L81>=0,Q81>=6,K81>=M81*0.25),"TRUE","FALSE") -> TRUE | Q81: =IFERROR(L81/(input!B7),0) -> 29.174667 | R81: flow_shock
A82: SCN002 | B82: Grad School 2yr | C82: 0 | D82: 0 | E82: =input!B5+0 -> 38 | F82: =input!B6*12 -> 57600 | G82: =input!B7*12 -> 36000 | H82: =F82-G82 -> 21600 | I82: =input!B11*12+MAX(0, MIN(input!B18, H82/12)) * 12 -> 33096 | J82: =calc_is!B13 -> 147952 | K82: =J82*(1+input!B14)+I82*((1+input!B14)-1)/input!B14 -> 191404.64 | L82: =input!B8 -> 19124 | M82: =calc_metrics!B4 -> 2499900 | N82: =IF(K82>=M82,"TRUE","FALSE") -> FALSE | O82: =IFERROR(K82/M82,0) -> 0.076564919 | P82: =IF(AND(L82>=0,Q82>=6,K82>=M82*0.25),"TRUE","FALSE") -> FALSE | Q82: =IFERROR(L82/(input!B7),0) -> 6.3746667 | R82: hybrid
A83: SCN002 | B83: Grad School 2yr | C83: 1 | D83: 1 | E83: =input!B5+1 -> 39 | F83: =input!B6*12 -> 57600 | G83: =input!B7*12 -> 36000 | H83: =F83-G83 -> 21600 | I83: =input!B11*12+MAX(0, MIN(input!B18, H83/12)) * 12 -> 33096 | J83: =K82 -> 191404.64 | K83: =J83*(1+input!B14)+I83*((1+input!B14)-1)/input!B14 -> 237898.96 | L83: =L82+MAX(0,H83/12) -> 20924 | M83: =calc_metrics!B4 -> 2499900 | N83: =IF(K83>=M83,"TRUE","FALSE") -> FALSE | O83: =IFERROR(K83/M83,0) -> 0.095163392 | P83: =IF(AND(L83>=0,Q83>=6,K83>=M83*0.25),"TRUE","FALSE") -> FALSE | Q83: =IFERROR(L83/(input!B7),0) -> 6.9746667 | R83: hybrid
A84: SCN002 | B84: Grad School 2yr | C84: 2 | D84: 2 | E84: =input!B5+2 -> 40 | F84: =input!B6*12*(1+input!G30) -> 28800 | G84: =( input!B7 + input!I30 ) * 12 -> 39600 | H84: =F84-G84 -> -10800 | I84: =0+MAX(0, MIN(input!B18+input!J30, H84/12)) * 12 -> 0 | J84: =K83 -> 237898.96 | K84: =J84*(1+input!B14)+I84*((1+input!B14)-1)/input!B14 -> 254551.89 | L84: =L83+MAX(0,H84/12)-input!H30 -> -19076 | M84: =calc_metrics!B4 -> 2499900 | N84: =IF(K84>=M84,"TRUE","FALSE") -> FALSE | O84: =IFERROR(K84/M84,0) -> 0.10182483 | P84: =IF(AND(L84>=0,Q84>=6,K84>=M84*0.25),"TRUE","FALSE") -> FALSE | Q84: =IFERROR(L84/(input!B7),0) -> -6.3586667 | R84: hybrid
A85: SCN002 | B85: Grad School 2yr | C85: 3 | D85: 3 | E85: =input!B5+3 -> 41 | F85: =input!B6*12*(1+input!G30) -> 28800 | G85: =( input!B7 + input!I30 ) * 12 -> 39600 | H85: =F85-G85 -> -10800 | I85: =0+MAX(0, MIN(input!B18+input!J30, H85/12)) * 12 -> 0 | J85: =K84 -> 254551.89 | K85: =J85*(1+input!B14)+I85*((1+input!B14)-1)/input!B14 -> 272370.52 | L85: =L84+MAX(0,H85/12) -> -19076 | M85: =calc_metrics!B4 -> 2499900 | N85: =IF(K85>=M85,"TRUE","FALSE") -> FALSE | O85: =IFERROR(K85/M85,0) -> 0.10895257 | P85: =IF(AND(L85>=0,Q85>=6,K85>=M85*0.25),"TRUE","FALSE") -> FALSE | Q85: =IFERROR(L85/(input!B7),0) -> -6.3586667 | R85: hybrid
A86: SCN002 | B86: Grad School 2yr | C86: 4 | D86: 4 | E86: =input!B5+4 -> 42 | F86: =input!B6*12 -> 57600 | G86: =input!B7*12 -> 36000 | H86: =F86-G86 -> 21600 | I86: =input!B11*12+MAX(0, MIN(input!B18, H86/12)) * 12 -> 33096 | J86: =K85 -> 272370.52 | K86: =J86*(1+input!B14)+I86*((1+input!B14)-1)/input!B14 -> 324532.46 | L86: =L85+MAX(0,H86/12) -> -17276 | M86: =calc_metrics!B4 -> 2499900 | N86: =IF(K86>=M86,"TRUE","FALSE") -> FALSE | O86: =IFERROR(K86/M86,0) -> 0.12981818 | P86: =IF(AND(L86>=0,Q86>=6,K86>=M86*0.25),"TRUE","FALSE") -> FALSE | Q86: =IFERROR(L86/(input!B7),0) -> -5.7586667 | R86: hybrid
A87: SCN002 | B87: Grad School 2yr | C87: 5 | D87: 5 | E87: =input!B5+5 -> 43 | F87: =input!B6*12 -> 57600 | G87: =input!B7*12 -> 36000 | H87: =F87-G87 -> 21600 | I87: =input!B11*12+MAX(0, MIN(input!B18, H87/12)) * 12 -> 33096 | J87: =K86 -> 324532.46 | K87: =J87*(1+input!B14)+I87*((1+input!B14)-1)/input!B14 -> 380345.73 | L87: =L86+MAX(0,H87/12) -> -15476 | M87: =calc_metrics!B4 -> 2499900 | N87: =IF(K87>=M87,"TRUE","FALSE") -> FALSE | O87: =IFERROR(K87/M87,0) -> 0.15214438 | P87: =IF(AND(L87>=0,Q87>=6,K87>=M87*0.25),"TRUE","FALSE") -> FALSE | Q87: =IFERROR(L87/(input!B7),0) -> -5.1586667 | R87: hybrid
A88: SCN002 | B88: Grad School 2yr | C88: 6 | D88: 6 | E88: =input!B5+6 -> 44 | F88: =input!B6*12 -> 57600 | G88: =input!B7*12 -> 36000 | H88: =F88-G88 -> 21600 | I88: =input!B11*12+MAX(0, MIN(input!B18, H88/12)) * 12 -> 33096 | J88: =K87 -> 380345.73 | K88: =J88*(1+input!B14)+I88*((1+input!B14)-1)/input!B14 -> 440065.94 | L88: =L87+MAX(0,H88/12) -> -13676 | M88: =calc_metrics!B4 -> 2499900 | N88: =IF(K88>=M88,"TRUE","FALSE") -> FALSE | O88: =IFERROR(K88/M88,0) -> 0.17603342 | P88: =IF(AND(L88>=0,Q88>=6,K88>=M88*0.25),"TRUE","FALSE") -> FALSE | Q88: =IFERROR(L88/(input!B7),0) -> -4.5586667 | R88: hybrid
A89: SCN002 | B89: Grad School 2yr | C89: 7 | D89: 7 | E89: =input!B5+7 -> 45 | F89: =input!B6*12 -> 57600 | G89: =input!B7*12 -> 36000 | H89: =F89-G89 -> 21600 | I89: =input!B11*12+MAX(0, MIN(input!B18, H89/12)) * 12 -> 33096 | J89: =K88 -> 440065.94 | K89: =J89*(1+input!B14)+I89*((1+input!B14)-1)/input!B14 -> 503966.55 | L89: =L88+MAX(0,H89/12) -> -11876 | M89: =calc_metrics!B4 -> 2499900 | N89: =IF(K89>=M89,"TRUE","FALSE") -> FALSE | O89: =IFERROR(K89/M89,0) -> 0.20159468 | P89: =IF(AND(L89>=0,Q89>=6,K89>=M89*0.25),"TRUE","FALSE") -> FALSE | Q89: =IFERROR(L89/(input!B7),0) -> -3.9586667 | R89: hybrid
A90: SCN002 | B90: Grad School 2yr | C90: 8 | D90: 8 | E90: =input!B5+8 -> 46 | F90: =input!B6*12 -> 57600 | G90: =input!B7*12 -> 36000 | H90: =F90-G90 -> 21600 | I90: =input!B11*12+MAX(0, MIN(input!B18, H90/12)) * 12 -> 33096 | J90: =K89 -> 503966.55 | K90: =J90*(1+input!B14)+I90*((1+input!B14)-1)/input!B14 -> 572340.21 | L90: =L89+MAX(0,H90/12) -> -10076 | M90: =calc_metrics!B4 -> 2499900 | N90: =IF(K90>=M90,"TRUE","FALSE") -> FALSE | O90: =IFERROR(K90/M90,0) -> 0.22894524 | P90: =IF(AND(L90>=0,Q90>=6,K90>=M90*0.25),"TRUE","FALSE") -> FALSE | Q90: =IFERROR(L90/(input!B7),0) -> -3.3586667 | R90: hybrid
A91: SCN002 | B91: Grad School 2yr | C91: 9 | D91: 9 | E91: =input!B5+9 -> 47 | F91: =input!B6*12 -> 57600 | G91: =input!B7*12 -> 36000 | H91: =F91-G91 -> 21600 | I91: =input!B11*12+MAX(0, MIN(input!B18, H91/12)) * 12 -> 33096 | J91: =K90 -> 572340.21 | K91: =J91*(1+input!B14)+I91*((1+input!B14)-1)/input!B14 -> 645500.02 | L91: =L90+MAX(0,H91/12) -> -8276 | M91: =calc_metrics!B4 -> 2499900 | N91: =IF(K91>=M91,"TRUE","FALSE") -> FALSE | O91: =IFERROR(K91/M91,0) -> 0.25821034 | P91: =IF(AND(L91>=0,Q91>=6,K91>=M91*0.25),"TRUE","FALSE") -> FALSE | Q91: =IFERROR(L91/(input!B7),0) -> -2.7586667 | R91: hybrid
A92: SCN002 | B92: Grad School 2yr | C92: 10 | D92: 10 | E92: =input!B5+10 -> 48 | F92: =input!B6*12 -> 57600 | G92: =input!B7*12 -> 36000 | H92: =F92-G92 -> 21600 | I92: =input!B11*12+MAX(0, MIN(input!B18, H92/12)) * 12 -> 33096 | J92: =K91 -> 645500.02 | K92: =J92*(1+input!B14)+I92*((1+input!B14)-1)/input!B14 -> 723781.03 | L92: =L91+MAX(0,H92/12) -> -6476 | M92: =calc_metrics!B4 -> 2499900 | N92: =IF(K92>=M92,"TRUE","FALSE") -> FALSE | O92: =IFERROR(K92/M92,0) -> 0.28952399 | P92: =IF(AND(L92>=0,Q92>=6,K92>=M92*0.25),"TRUE","FALSE") -> FALSE | Q92: =IFERROR(L92/(input!B7),0) -> -2.1586667 | R92: hybrid
A93: SCN002 | B93: Grad School 2yr | C93: 11 | D93: 11 | E93: =input!B5+11 -> 49 | F93: =input!B6*12 -> 57600 | G93: =input!B7*12 -> 36000 | H93: =F93-G93 -> 21600 | I93: =input!B11*12+MAX(0, MIN(input!B18, H93/12)) * 12 -> 33096 | J93: =K92 -> 723781.03 | K93: =J93*(1+input!B14)+I93*((1+input!B14)-1)/input!B14 -> 807541.7 | L93: =L92+MAX(0,H93/12) -> -4676 | M93: =calc_metrics!B4 -> 2499900 | N93: =IF(K93>=M93,"TRUE","FALSE") -> FALSE | O93: =IFERROR(K93/M93,0) -> 0.3230296 | P93: =IF(AND(L93>=0,Q93>=6,K93>=M93*0.25),"TRUE","FALSE") -> FALSE | Q93: =IFERROR(L93/(input!B7),0) -> -1.5586667 | R93: hybrid
A94: SCN002 | B94: Grad School 2yr | C94: 12 | D94: 12 | E94: =input!B5+12 -> 50 | F94: =input!B6*12 -> 57600 | G94: =input!B7*12 -> 36000 | H94: =F94-G94 -> 21600 | I94: =input!B11*12+MAX(0, MIN(input!B18, H94/12)) * 12 -> 33096 | J94: =K93 -> 807541.7 | K94: =J94*(1+input!B14)+I94*((1+input!B14)-1)/input!B14 -> 897165.62 | L94: =L93+MAX(0,H94/12) -> -2876 | M94: =calc_metrics!B4 -> 2499900 | N94: =IF(K94>=M94,"TRUE","FALSE") -> FALSE | O94: =IFERROR(K94/M94,0) -> 0.3588806 | P94: =IF(AND(L94>=0,Q94>=6,K94>=M94*0.25),"TRUE","FALSE") -> FALSE | Q94: =IFERROR(L94/(input!B7),0) -> -0.95866667 | R94: hybrid
A95: SCN002 | B95: Grad School 2yr | C95: 13 | D95: 13 | E95: =input!B5+13 -> 51 | F95: =input!B6*12 -> 57600 | G95: =input!B7*12 -> 36000 | H95: =F95-G95 -> 21600 | I95: =input!B11*12+MAX(0, MIN(input!B18, H95/12)) * 12 -> 33096 | J95: =K94 -> 897165.62 | K95: =J95*(1+input!B14)+I95*((1+input!B14)-1)/input!B14 -> 993063.21 | L95: =L94+MAX(0,H95/12) -> -1076 | M95: =calc_metrics!B4 -> 2499900 | N95: =IF(K95>=M95,"TRUE","FALSE") -> FALSE | O95: =IFERROR(K95/M95,0) -> 0.39724117 | P95: =IF(AND(L95>=0,Q95>=6,K95>=M95*0.25),"TRUE","FALSE") -> FALSE | Q95: =IFERROR(L95/(input!B7),0) -> -0.35866667 | R95: hybrid
A96: SCN002 | B96: Grad School 2yr | C96: 14 | D96: 14 | E96: =input!B5+14 -> 52 | F96: =input!B6*12 -> 57600 | G96: =input!B7*12 -> 36000 | H96: =F96-G96 -> 21600 | I96: =input!B11*12+MAX(0, MIN(input!B18, H96/12)) * 12 -> 33096 | J96: =K95 -> 993063.21 | K96: =J96*(1+input!B14)+I96*((1+input!B14)-1)/input!B14 -> 1095673.6 | L96: =L95+MAX(0,H96/12) -> 724 | M96: =calc_metrics!B4 -> 2499900 | N96: =IF(K96>=M96,"TRUE","FALSE") -> FALSE | O96: =IFERROR(K96/M96,0) -> 0.43828699 | P96: =IF(AND(L96>=0,Q96>=6,K96>=M96*0.25),"TRUE","FALSE") -> FALSE | Q96: =IFERROR(L96/(input!B7),0) -> 0.24133333 | R96: hybrid
A97: SCN002 | B97: Grad School 2yr | C97: 15 | D97: 15 | E97: =input!B5+15 -> 53 | F97: =input!B6*12 -> 57600 | G97: =input!B7*12 -> 36000 | H97: =F97-G97 -> 21600 | I97: =input!B11*12+MAX(0, MIN(input!B18, H97/12)) * 12 -> 33096 | J97: =K96 -> 1095673.6 | K97: =J97*(1+input!B14)+I97*((1+input!B14)-1)/input!B14 -> 1205466.8 | L97: =L96+MAX(0,H97/12) -> 2524 | M97: =calc_metrics!B4 -> 2499900 | N97: =IF(K97>=M97,"TRUE","FALSE") -> FALSE | O97: =IFERROR(K97/M97,0) -> 0.482206 | P97: =IF(AND(L97>=0,Q97>=6,K97>=M97*0.25),"TRUE","FALSE") -> FALSE | Q97: =IFERROR(L97/(input!B7),0) -> 0.84133333 | R97: hybrid
A98: SCN002 | B98: Grad School 2yr | C98: 16 | D98: 16 | E98: =input!B5+16 -> 54 | F98: =input!B6*12 -> 57600 | G98: =input!B7*12 -> 36000 | H98: =F98-G98 -> 21600 | I98: =input!B11*12+MAX(0, MIN(input!B18, H98/12)) * 12 -> 33096 | J98: =K97 -> 1205466.8 | K98: =J98*(1+input!B14)+I98*((1+input!B14)-1)/input!B14 -> 1322945.5 | L98: =L97+MAX(0,H98/12) -> 4324 | M98: =calc_metrics!B4 -> 2499900 | N98: =IF(K98>=M98,"TRUE","FALSE") -> FALSE | O98: =IFERROR(K98/M98,0) -> 0.52919935 | P98: =IF(AND(L98>=0,Q98>=6,K98>=M98*0.25),"TRUE","FALSE") -> FALSE | Q98: =IFERROR(L98/(input!B7),0) -> 1.4413333 | R98: hybrid
A99: SCN002 | B99: Grad School 2yr | C99: 17 | D99: 17 | E99: =input!B5+17 -> 55 | F99: =input!B6*12 -> 57600 | G99: =input!B7*12 -> 36000 | H99: =F99-G99 -> 21600 | I99: =input!B11*12+MAX(0, MIN(input!B18, H99/12)) * 12 -> 33096 | J99: =K98 -> 1322945.5 | K99: =J99*(1+input!B14)+I99*((1+input!B14)-1)/input!B14 -> 1448647.6 | L99: =L98+MAX(0,H99/12) -> 6124 | M99: =calc_metrics!B4 -> 2499900 | N99: =IF(K99>=M99,"TRUE","FALSE") -> FALSE | O99: =IFERROR(K99/M99,0) -> 0.57948224 | P99: =IF(AND(L99>=0,Q99>=6,K99>=M99*0.25),"TRUE","FALSE") -> FALSE | Q99: =IFERROR(L99/(input!B7),0) -> 2.0413333 | R99: hybrid
A100: SCN002 | B100: Grad School 2yr | C100: 18 | D100: 18 | E100: =input!B5+18 -> 56 | F100: =input!B6*12 -> 57600 | G100: =input!B7*12 -> 36000 | H100: =F100-G100 -> 21600 | I100: =input!B11*12+MAX(0, MIN(input!B18, H100/12)) * 12 -> 33096 | J100: =K99 -> 1448647.6 | K100: =J100*(1+input!B14)+I100*((1+input!B14)-1)/input!B14 -> 1583149 | L100: =L99+MAX(0,H100/12) -> 7924 | M100: =calc_metrics!B4 -> 2499900 | N100: =IF(K100>=M100,"TRUE","FALSE") -> FALSE | O100: =IFERROR(K100/M100,0) -> 0.63328492 | P100: =IF(AND(L100>=0,Q100>=6,K100>=M100*0.25),"TRUE","FALSE") -> FALSE | Q100: =IFERROR(L100/(input!B7),0) -> 2.6413333 | R100: hybrid
...

Sheet scenarios_def
A1: SCENARIO DEFINITIONS (reference only — edit in input sheet)
A2: scenario_id | B2: scenario_name | C2: scenario_type | D2: active_flag | E2: pause_401k | F2: start_offset_yr | G2: duration_mo | H2: income_change_pct | I2: one_time_cost | J2: expense_delta_mo | K2: recovery_income_pct
A3: SCN000 | B3: =input!A28 -> Baseline | C3: =input!B28 -> baseline | D3: =input!C28 -> TRUE | E3: =input!D28 -> FALSE | F3: =input!E28 -> 0 | G3: =input!F28 -> 0 | H3: =input!G28 -> 0 | I3: =input!H28 -> 0 | ... K3: =input!J28 -> 0
A4: SCN001 | B4: =input!A29 -> Career Break 1yr | C4: =input!B29 -> flow_shock | D4: =input!C29 -> TRUE | E4: =input!D29 -> TRUE | F4: =input!E29 -> 1 | G4: =input!F29 -> 12 | H4: =input!G29 -> -1 | I4: =input!H29 -> 0 | ... K4: =input!J29 -> -800
A5: SCN002 | B5: =input!A30 -> Grad School 2yr | C5: =input!B30 -> hybrid | D5: =input!C30 -> TRUE | E5: =input!D30 -> TRUE | F5: =input!E30 -> 2 | G5: =input!F30 -> 24 | H5: =input!G30 -> -0.5 | I5: =input!H30 -> 40000 | ... K5: =input!J30 -> -800
A6: SCN003 | B6: =input!A31 -> Family Planning | C6: =input!B31 -> flow_shock | D6: =input!C31 -> TRUE | E6: =input!D31 -> FALSE | F6: =input!E31 -> 1 | G6: =input!F31 -> 12 | H6: =input!G31 -> 0 | I6: =input!H31 -> 0 | ... K6: =input!J31 -> 0
A8: scenario_type ENUM: baseline | flow_shock | stock_shock | hybrid
A9: flow_shock: IS impact (income/expense change) | stock_shock: BS direct (one_time_cost) | hybrid: both
